[{"id": 946, "created_at": "2021-11-01T15:51:43.751120", "updated_at": "2022-11-06T23:18:45.205871", "slug": "rasa-libre-a-cosmic-experience", "title": "Rasa Libre - A Cosmic Experience", "image_url": "https://assets.skatevideo.site/covers/rasa-libre-a-cosmic-experience-5677.jpg", "description": "", "year": 2008, "time": 17, "trailer": "http://www.youtube.com/watch?v=PwOwzwjtMQ0", "videolink": "https://youtu.be/iGh0pIBJv-g", "date": null, "is_active": true, "links": [], "category": {"id": 2, "name": "promo"}, "filmmakers": [], "companies": [{"id": 129, "name": "rasa libre", "slug": "rasa-libre"}], "country": {"id": 4, "name": "United States"}, "soundtracks": [{"id": 10241, "videoid": 946, "section": "Intro", "track": "?", "sort": 1}, {"id": 10242, "videoid": 946, "section": "Jon Newport & Ryan Lay", "track": "The Animals - A Girl Named Sandoz", "sort": 2}, {"id": 10243, "videoid": 946, "section": "Bryan Botelho & Nate Jones", "track": "Grateful Dead - Scarlet Begonias", "sort": 3}, {"id": 10244, "videoid": 946, "section": "Family", "track": "Grateful Dead - We Bid You Goodnight", "sort": 4}, {"id": 10245, "videoid": 946, "section": "Kenny Reed & Mike Daher", "track": "Grateful Dead - Althea", "sort": 5}, {"id": 10246, "videoid": 946, "section": "Ben Gore", "track": "Doug Martsch - Instrumental", "sort": 6}, {"id": 10247, "videoid": 946, "section": "Matt Field & Outro", "track": "Paul Kantner - The Mountain Song", "sort": 7}, {"id": 22543, "videoid": 946, "section": "Trailer", "track": "Grateful Dead - Fire On The Mountain", "sort": 8}], "skaters": [{"id": 1929, "name": "ryan lay", "slug": "ryan-lay"}, {"id": 1293, "name": "mike daher", "slug": "mike-daher"}, {"id": 615, "name": "matt field", "slug": "matt-field"}, {"id": 64, "name": "kenny reed", "slug": "kenny-reed"}, {"id": 2643, "name": "bryan botelho", "slug": "bryan-botelho"}, {"id": 340, "name": "ben gore", "slug": "ben-gore"}, {"id": 388, "name": "jon newport", "slug": "jon-newport"}], "tags": []}, {"id": 1160, "created_at": "2021-11-01T15:51:43.751120", "updated_at": "2021-11-01T15:51:43.751120", "slug": "skateparks-of-oregon-ecuador", "title": "Skateparks of Oregon/Ecuador", "image_url": "https://assets.skatevideo.site/covers/skateparks-of-oregon-ecuador.jpg", "description": "", "year": 2001, "time": 60, "trailer": "", "videolink": "", "date": null, "is_active": true, "links": null, "category": {"id": 4, "name": "documentary"}, "filmmakers": [], "companies": [{"id": 321, "name": "nichols charnoski", "slug": "nichols-charnoski"}], "country": {"id": 4, "name": "United States"}, "soundtracks": [], "skaters": [{"id": 789, "name": "steve bailey", "slug": "steve-bailey"}, {"id": 417, "name": "peter hewitt", "slug": "peter-hewitt"}, {"id": 571, "name": "sam hitz", "slug": "sam-hitz"}, {"id": 3031, "name": "mark hubbard (\"monk\")", "slug": "mark-hubbard-monk"}, {"id": 3036, "name": "brewce martin", "slug": "brewce-martin"}, {"id": 842, "name": "david palmer", "slug": "david-palmer"}, {"id": 568, "name": "al partanen", "slug": "al-partanen"}, {"id": 345, "name": "bobby puleo", "slug": "bobby-puleo"}, {"id": 3037, "name": "tino razo", "slug": "tino-razo"}, {"id": 2771, "name": "mark scott (\"red\")", "slug": "mark-scott-red"}, {"id": 840, "name": "scott smiley", "slug": "scott-smiley"}], "tags": []}, {"id": 1166, "created_at": "2021-11-01T15:51:43.751120", "updated_at": "2021-11-01T15:51:43.751120", "slug": "planet-earth-animal-farm", "title": "Planet Earth - Animal Farm", "image_url": "https://assets.skatevideo.site/covers/planet-earth-animal-farm.jpg", "description": "", "year": 1993, "time": 13, "trailer": "", "videolink": "", "date": null, "is_active": true, "links": null, "category": {"id": 2, "name": "promo"}, "filmmakers": [], "companies": [{"id": 84, "name": "planet earth clothing", "slug": "planet-earth-clothing"}], "country": {"id": 0, "name": "Unknown"}, "soundtracks": [{"id": 11525, "videoid": 1166, "section": "", "track": "John Williams - Star Wars Theme", "sort": 1}], "skaters": [{"id": 62, "name": "kenny anderson", "slug": "kenny-anderson"}, {"id": 1121, "name": "felix arguelles", "slug": "felix-arguelles"}, {"id": 1128, "name": "barker barrett", "slug": "barker-barrett"}, {"id": 1073, "name": "jason carney", "slug": "jason-carney"}, {"id": 1133, "name": "buster halterman", "slug": "buster-halterman"}, {"id": 1645, "name": "ricky higgins", "slug": "ricky-higgins"}, {"id": 1018, "name": "brian howard", "slug": "brian-howard"}, {"id": 1123, "name": "lib layraman", "slug": "lib-layraman"}, {"id": 3044, "name": "ted lee", "slug": "ted-lee"}, {"id": 1124, "name": "mirko mangum", "slug": "mirko-mangum"}, {"id": 1135, "name": "chris miller", "slug": "chris-miller"}, {"id": 3045, "name": "david mills", "slug": "david-mills"}, {"id": 1127, "name": "paul shapiro", "slug": "paul-shapiro"}, {"id": 874, "name": "mark wyndham", "slug": "mark-wyndham"}], "tags": []}, {"id": 1164, "created_at": "2021-11-01T15:51:43.751120", "updated_at": "2021-11-01T15:51:43.751120", "slug": "pig-all-systems-go", "title": "Pig - All Systems Go!", "image_url": "https://assets.skatevideo.site/covers/pig-all-systems-go.jpg", "description": "", "year": 1998, "time": 26, "trailer": "", "videolink": "", "date": null, "is_active": true, "links": null, "category": {"id": 11, "name": "full-length"}, "filmmakers": [], "companies": [{"id": 182, "name": "pig wheels", "slug": "pig-wheels"}], "country": {"id": 0, "name": "Unknown"}, "soundtracks": [{"id": 31423, "videoid": 1164, "section": "Opening Montage", "track": "Starpower", "sort": 1}, {"id": 31424, "videoid": 1164, "section": "Jon West", "track": "Nirvana", "sort": 2}, {"id": 31425, "videoid": 1164, "section": "Vinnie Ponte", "track": "AC/DC", "sort": 3}, {"id": 31426, "videoid": 1164, "section": "Jason Adams #1", "track": "Fu Manchu", "sort": 4}, {"id": 31427, "videoid": 1164, "section": "Jason Adams #2", "track": "Mar...or Astroman?", "sort": 5}, {"id": 31428, "videoid": 1164, "section": "Josh Beagle", "track": "Dwarves", "sort": 6}, {"id": 31429, "videoid": 1164, "section": "Jerry Fowler", "track": "Firehorse", "sort": 7}, {"id": 31430, "videoid": 1164, "section": "Team Montage", "track": "The Damned", "sort": 8}, {"id": 31431, "videoid": 1164, "section": "Dave Mayhew", "track": "James Taylor Quartet", "sort": 9}, {"id": 31432, "videoid": 1164, "section": "Dorian Tucker", "track": "Love", "sort": 10}, {"id": 31433, "videoid": 1164, "section": "Pat Channita", "track": "Supersuckers", "sort": 11}, {"id": 31434, "videoid": 1164, "section": "Ryan Bartsma", "track": "Man...or Astroman?", "sort": 12}, {"id": 31435, "videoid": 1164, "section": "Friends", "track": "Melvins", "sort": 13}, {"id": 31436, "videoid": 1164, "section": "Satva Leung", "track": "The Damned", "sort": 14}, {"id": 31437, "videoid": 1164, "section": "Chad Knight", "track": "Didjits", "sort": 15}, {"id": 31438, "videoid": 1164, "section": "Closing Montage", "track": "Man...or Astroman", "sort": 16}], "skaters": [{"id": 260, "name": "jason adams (\"the kid\")", "slug": "jason-adams-the-kid"}, {"id": 1524, "name": "ryan bartsma", "slug": "ryan-bartsma"}, {"id": 249, "name": "josh beagle", "slug": "josh-beagle"}, {"id": 622, "name": "pat channita", "slug": "pat-channita"}, {"id": 90, "name": "ronnie creager", "slug": "ronnie-creager"}, {"id": 1122, "name": "jerry fowler", "slug": "jerry-fowler"}, {"id": 616, "name": "matt hensley", "slug": "matt-hensley"}, {"id": 971, "name": "chad knight", "slug": "chad-knight"}, {"id": 558, "name": "satva leung", "slug": "satva-leung"}, {"id": 950, "name": "jason maxwell", "slug": "jason-maxwell"}, {"id": 972, "name": "dave mayhew", "slug": "dave-mayhew"}, {"id": 1328, "name": "vinny ponte", "slug": "vinny-ponte"}, {"id": 122, "name": "chris senn", "slug": "chris-senn"}, {"id": 593, "name": "brad staba", "slug": "brad-staba"}, {"id": 135, "name": "elissa steamer", "slug": "elissa-steamer"}, {"id": 1054, "name": "dorian tucker", "slug": "dorian-tucker"}, {"id": 827, "name": "jon west", "slug": "jon-west"}], "tags": []}, {"id": 1156, "created_at": "2021-11-01T15:51:43.751120", "updated_at": "2021-11-01T15:51:43.751120", "slug": "new-school", "title": "New School", "image_url": "https://assets.skatevideo.site/covers/new-school.jpg", "description": "", "year": 1993, "time": 14, "trailer": "", "videolink": "", "date": null, "is_active": true, "links": null, "category": {"id": 13, "name": "productions"}, "filmmakers": [], "companies": [{"id": 942, "name": "New School Skateboards", "slug": "New-School-Skateboards"}], "country": {"id": 0, "name": "Unknown"}, "soundtracks": [{"id": 11502, "videoid": 1156, "section": "", "track": "Beastie Boys - Shake Your Rump", "sort": 1}, {"id": 11503, "videoid": 1156, "section": "", "track": "Brenton Wood - Gimme A Little Sign", "sort": 2}, {"id": 11504, "videoid": 1156, "section": "", "track": "Simon and Garfunkel - I Am a Rock", "sort": 3}, {"id": 11505, "videoid": 1156, "section": "", "track": "Stevie Wonder - We Can Work It Out", "sort": 4}, {"id": 11506, "videoid": 1156, "section": "", "track": "Faction - California Dreamin'", "sort": 5}, {"id": 11507, "videoid": 1156, "section": "", "track": "Pegboy - Strong Reaction", "sort": 6}], "skaters": [{"id": 819, "name": "tom boyle", "slug": "tom-boyle"}, {"id": 3028, "name": "mike chu", "slug": "mike-chu"}, {"id": 3029, "name": "jim duhamel", "slug": "jim-duhamel"}, {"id": 3030, "name": "alan lo", "slug": "alan-lo"}, {"id": 822, "name": "pete mihalenko", "slug": "pete-mihalenko"}], "tags": []}, {"id": 3697, "created_at": "2021-11-20T02:08:12.692777", "updated_at": "2022-03-24T00:20:47.297427", "slug": "rvca-the-balance-of-opposites", "title": "RVCA - The Balance of Opposites", "image_url": "https://assets.skatevideo.site/covers/rvca-the-balance-of-opposites.jpg", "description": null, "year": 2019, "time": 29, "trailer": "https://www.youtube.com/watch?v=SG84k82Xg9Y", "videolink": "https://www.youtube.com/watch?v=2mD1LPva4YQ", "date": "2020-01-07T22:16:32+00:00", "is_active": true, "links": null, "category": {"id": 11, "name": "full-length"}, "filmmakers": [{"id": 159, "name": "Brandon Jensen", "slug": "brandon-jensen"}, {"id": 198, "name": "Don Luong", "slug": "don-luong"}], "companies": [{"id": 461, "name": "RVCA", "slug": "RVCA"}], "country": {"id": 4, "name": "United States"}, "soundtracks": [{"id": 35207, "videoid": 3697, "section": "Intro", "track": "Turkish Circus - Freckles", "sort": 1}, {"id": 35208, "videoid": 3697, "section": "Zach Allen", "track": "Khruangbin - People Everywhere (Still Alive)", "sort": 2}, {"id": 35209, "videoid": 3697, "section": "Kevin \"Spanky\" Long", "track": "Cass Mccombs - Oatmeal", "sort": 3}, {"id": 35210, "videoid": 3697, "section": "Andrew Reynolds", "track": "Panda Bear - Untying The Knot", "sort": 4}, {"id": 35211, "videoid": 3697, "section": "", "track": "Montage 1 - ?", "sort": 5}, {"id": 35212, "videoid": 3697, "section": "", "track": "Montage 2 - ?", "sort": 6}, {"id": 35213, "videoid": 3697, "section": "Transition Section", "track": "Black Cobra - The Cry Of Melora", "sort": 7}, {"id": 35214, "videoid": 3697, "section": "Curren Caples, Greyson Fletcher & More", "track": "Part Time - The Ballad Of Jean", "sort": 8}, {"id": 35215, "videoid": 3697, "section": "Mark Suciu", "track": "Amen Dunes - Blue Rose", "sort": 9}, {"id": 35216, "videoid": 3697, "section": "Julian Davidson", "track": "Cocteau Twins - Pearly Dewdrops' Dew", "sort": 10}, {"id": 35217, "videoid": 3697, "section": "Credits", "track": "?", "sort": 11}], "skaters": [{"id": 9011, "name": "aidan campbell", "slug": "aidan-campbell"}, {"id": 104, "name": "andrew reynolds (\"the boss\")", "slug": "andrew-reynolds-the-boss"}, {"id": 4510, "name": "curren caples", "slug": "curren-caples"}, {"id": 7725, "name": "greyson fletcher", "slug": "greyson-fletcher"}, {"id": 8060, "name": "jeremy leabres", "slug": "jeremy-leabres"}, {"id": 2642, "name": "julian davidson", "slug": "julian-davidson"}, {"id": 5274, "name": "Mark Suciu", "slug": "Mark-Suciu"}, {"id": 1147, "name": "nestor judkins", "slug": "nestor-judkins"}, {"id": 11539, "name": "zach allen", "slug": "zach-allen"}, {"id": 65, "name": "kevin long (\"spanky\")", "slug": "kevin-long-spanky"}], "tags": []}, {"id": 1187, "created_at": "2021-11-01T15:51:43.751120", "updated_at": "2021-11-01T15:51:43.751120", "slug": "santa-cruz-speed-freaks", "title": "Santa Cruz - Speed Freaks", "image_url": "https://assets.skatevideo.site/covers/santa-cruz-speed-freaks.jpg", "description": "", "year": 1989, "time": 72, "trailer": "", "videolink": "", "date": null, "is_active": true, "links": null, "category": {"id": 11, "name": "full-length"}, "filmmakers": [], "companies": [{"id": 39, "name": "santa cruz skateboards", "slug": "santa-cruz-skateboards"}], "country": {"id": 0, "name": "Unknown"}, "soundtracks": [], "skaters": [{"id": 3114, "name": "jimmy acosta", "slug": "jimmy-acosta"}, {"id": 1240, "name": "steve alba", "slug": "steve-alba"}, {"id": 1038, "name": "ron allen", "slug": "ron-allen"}, {"id": 420, "name": "neil blender", "slug": "neil-blender"}, {"id": 3115, "name": "brian brannon", "slug": "brian-brannon"}, {"id": 724, "name": "eric dressen", "slug": "eric-dressen"}, {"id": 3116, "name": "don fisher", "slug": "don-fisher"}, {"id": 883, "name": "john gibson", "slug": "john-gibson"}, {"id": 605, "name": "jeff grosso", "slug": "jeff-grosso"}, {"id": 1222, "name": "jeff hedges", "slug": "jeff-hedges"}, {"id": 1243, "name": "christian hosoi", "slug": "christian-hosoi"}, {"id": 926, "name": "jason jessee", "slug": "jason-jessee"}, {"id": 618, "name": "natas kaupas", "slug": "natas-kaupas"}, {"id": 1224, "name": "jeff kendall", "slug": "jeff-kendall"}, {"id": 1225, "name": "tom knox (usa)", "slug": "tom-knox-usa"}, {"id": 1044, "name": "tony magnusson", "slug": "tony-magnusson"}, {"id": 1881, "name": "ken mcGuire", "slug": "ken-mcGuire"}, {"id": 2785, "name": "arron murray", "slug": "arron-murray"}, {"id": 2043, "name": "monty nolder", "slug": "monty-nolder"}, {"id": 1813, "name": "corey o'Brien", "slug": "corey-oBrien"}, {"id": 2005, "name": "scott oster", "slug": "scott-oster"}, {"id": 2852, "name": "bryan pennington", "slug": "bryan-pennington"}, {"id": 2837, "name": "jeff phillips", "slug": "jeff-phillips"}, {"id": 3118, "name": "anders pulpanek", "slug": "anders-pulpanek"}, {"id": 1242, "name": "rob roskopp", "slug": "rob-roskopp"}, {"id": 2008, "name": "reese simpson", "slug": "reese-simpson"}, {"id": 3119, "name": "butch sterbins", "slug": "butch-sterbins"}, {"id": 1195, "name": "jim thiebaud", "slug": "jim-thiebaud"}, {"id": 169, "name": "mike vallely", "slug": "mike-vallely"}, {"id": 129, "name": "danny way", "slug": "danny-way"}, {"id": 1046, "name": "david nielsen", "slug": "david-nielsen"}], "tags": []}, {"id": 1188, "created_at": "2021-11-01T15:51:43.751120", "updated_at": "2021-11-01T15:51:43.751120", "slug": "santa-cruz-wheels-of-fire", "title": "Santa Cruz - Wheels of Fire", "image_url": "https://assets.skatevideo.site/covers/santa-cruz-wheels-of-fire.jpg", "description": "", "year": 1987, "time": 42, "trailer": "", "videolink": "", "date": null, "is_active": true, "links": null, "category": {"id": 11, "name": "full-length"}, "filmmakers": [], "companies": [{"id": 39, "name": "santa cruz skateboards", "slug": "santa-cruz-skateboards"}], "country": {"id": 0, "name": "Unknown"}, "soundtracks": [], "skaters": [{"id": 1240, "name": "steve alba", "slug": "steve-alba"}, {"id": 1241, "name": "claus grabke", "slug": "claus-grabke"}, {"id": 1243, "name": "christian hosoi", "slug": "christian-hosoi"}, {"id": 618, "name": "natas kaupas", "slug": "natas-kaupas"}, {"id": 1224, "name": "jeff kendall", "slug": "jeff-kendall"}, {"id": 1242, "name": "rob roskopp", "slug": "rob-roskopp"}], "tags": []}, {"id": 1169, "created_at": "2021-11-01T15:51:43.751120", "updated_at": "2021-11-01T15:51:43.751120", "slug": "platinum-crimes-and-misdemeanors", "title": "Platinum - Crimes & Misdemeanors", "image_url": "https://assets.skatevideo.site/covers/platinum-crimes-and-misdemeanors.jpg", "description": "", "year": 0, "time": 10, "trailer": "", "videolink": "", "date": null, "is_active": true, "links": null, "category": {"id": 2, "name": "promo"}, "filmmakers": [], "companies": [{"id": 676, "name": "platinum skateboards", "slug": "platinum-skateboards"}], "country": {"id": 0, "name": "Unknown"}, "soundtracks": [{"id": 11544, "videoid": 1169, "section": "Intro", "track": "Inner Circle - Bad Boys", "sort": 1}, {"id": 11545, "videoid": 1169, "section": "Arto Saari", "track": "Elvis Costello - Watching The Detective", "sort": 2}, {"id": 22282, "videoid": 1169, "section": "Neal Mims", "track": "?", "sort": 3}, {"id": 11546, "videoid": 1169, "section": "Jake Stewart", "track": "Iggy Pop - Starry Night", "sort": 4}, {"id": 11547, "videoid": 1169, "section": "Moses Itkonen", "track": "The Clash - Guns of Brixton", "sort": 5}, {"id": 11548, "videoid": 1169, "section": "Paul Machnau", "track": "ZZ Top - Sharp Dressed Man", "sort": 6}, {"id": 22281, "videoid": 1169, "section": "Credits", "track": "?", "sort": 7}], "skaters": [{"id": 278, "name": "moses itkonen", "slug": "moses-itkonen"}, {"id": 284, "name": "paul machnau", "slug": "paul-machnau"}, {"id": 701, "name": "neal mims", "slug": "neal-mims"}, {"id": 1, "name": "arto saari", "slug": "arto-saari"}, {"id": 707, "name": "jake stewart", "slug": "jake-stewart"}], "tags": []}, {"id": 3619, "created_at": "2021-11-13T00:55:36.410617", "updated_at": "2021-11-13T00:55:36.410617", "slug": "dc-cargo-sneaker", "title": "DC - Cargo Sneaker", "image_url": "https://assets.skatevideo.site/covers/dc-cargo-sneaker.jpg", "description": null, "year": 2020, "time": 4, "trailer": null, "videolink": "https://www.youtube.com/watch?v=wWTOm-ZFY3w", "date": "2020-11-19T02:26:08+00:00", "is_active": true, "links": null, "category": {"id": 18, "name": "solo part"}, "filmmakers": [{"id": 601, "name": "Brian Panebianco", "slug": "brian-panebianco"}], "companies": [{"id": 18, "name": "DC shoes", "slug": "DC-shoes"}], "country": null, "soundtracks": [{"id": 34617, "videoid": 3619, "section": "", "track": "Eli Morgan Gesner - Condemned Yet Exalted", "sort": 0}], "skaters": [{"id": 10538, "name": "john shanahan", "slug": "john-shanahan"}], "tags": []}, {"id": 1128, "created_at": "2021-11-01T15:51:43.751120", "updated_at": "2022-04-01T01:05:05.749934", "slug": "technical-support", "title": "Technical Support", "image_url": "https://assets.skatevideo.site/covers/technical-support.jpg", "description": "", "year": 2003, "time": 90, "trailer": "", "videolink": "", "date": null, "is_active": true, "links": null, "category": {"id": 1, "name": "independent"}, "filmmakers": [], "companies": [{"id": 373, "name": "falconskates productions", "slug": "falconskates-productions"}], "country": {"id": 4, "name": "United States"}, "soundtracks": [{"id": 11405, "videoid": 1128, "section": "", "track": "Stage Dive - Outside of Love", "sort": 1}, {"id": 11406, "videoid": 1128, "section": "", "track": "Stage Dive - Technical Support", "sort": 2}, {"id": 11407, "videoid": 1128, "section": "", "track": "Stage Dive - Celebrity", "sort": 3}, {"id": 11408, "videoid": 1128, "section": "", "track": "Stage Dive - Let Go", "sort": 4}, {"id": 11409, "videoid": 1128, "section": "", "track": "Stage Dive - Unneccessary Information", "sort": 5}, {"id": 11410, "videoid": 1128, "section": "", "track": "Stage Dive - Dance", "sort": 6}, {"id": 11411, "videoid": 1128, "section": "", "track": "Stage Dive - Sick", "sort": 7}, {"id": 11412, "videoid": 1128, "section": "", "track": "Stage Dive - Now", "sort": 8}, {"id": 11413, "videoid": 1128, "section": "", "track": "Stage Dive - Suck You", "sort": 9}, {"id": 11414, "videoid": 1128, "section": "", "track": "Stage Dive - All the Same", "sort": 10}, {"id": 11415, "videoid": 1128, "section": "", "track": "Stage Dive - Angry", "sort": 11}, {"id": 11416, "videoid": 1128, "section": "", "track": "Stage Dive - Left Behind", "sort": 12}, {"id": 11417, "videoid": 1128, "section": "", "track": "Stage Dive - Friend", "sort": 13}, {"id": 11418, "videoid": 1128, "section": "", "track": "Stage Dive - Empty", "sort": 14}, {"id": 11419, "videoid": 1128, "section": "", "track": "Stage Dive - Remind", "sort": 15}, {"id": 11420, "videoid": 1128, "section": "", "track": "Stage Dive - Poison", "sort": 16}, {"id": 11421, "videoid": 1128, "section": "", "track": "Stage Dive - Sunshine Girl", "sort": 17}, {"id": 11422, "videoid": 1128, "section": "", "track": "Stage Dive - Mistyfied", "sort": 18}, {"id": 11423, "videoid": 1128, "section": "", "track": "Stage Dive - Candyland", "sort": 19}, {"id": 11424, "videoid": 1128, "section": "", "track": "Stage Dive - Perfect Song 2.0", "sort": 20}, {"id": 11425, "videoid": 1128, "section": "", "track": "Stage Dive - Begin", "sort": 21}, {"id": 11426, "videoid": 1128, "section": "", "track": "Stage Dive - Tell Me", "sort": 22}], "skaters": [{"id": 2946, "name": "todd falcon", "slug": "todd-falcon"}, {"id": 2947, "name": "hurvey haskins", "slug": "hurvey-haskins"}, {"id": 2948, "name": "daniel macFarlane", "slug": "daniel-macFarlane"}], "tags": []}, {"id": 1179, "created_at": "2021-11-01T15:51:43.751120", "updated_at": "2023-03-11T21:45:31.587173", "slug": "real-non-fiction", "title": "Real - Non-Fiction", "image_url": "https://assets.skatevideo.site/covers/real-non-fiction.jpg", "description": "", "year": 1997, "time": 42, "trailer": "", "videolink": "", "date": null, "is_active": true, "links": [], "category": {"id": 11, "name": "full-length"}, "filmmakers": [], "companies": [{"id": 37, "name": "real skateboards", "slug": "real-skateboards"}], "country": {"id": 0, "name": "Unknown"}, "soundtracks": [], "skaters": [{"id": 1116, "name": "joey bast", "slug": "joey-bast"}, {"id": 1190, "name": "kelly bird", "slug": "kelly-bird"}, {"id": 1199, "name": "mike cardona", "slug": "mike-cardona"}, {"id": 624, "name": "quim cardona", "slug": "quim-cardona"}, {"id": 615, "name": "matt field", "slug": "matt-field"}, {"id": 71, "name": "mark gonzales (\"gonz\")", "slug": "mark-gonzales-gonz"}, {"id": 1174, "name": "tommy guerrero", "slug": "tommy-guerrero"}, {"id": 61, "name": "keith hufnagel (\"huf\")", "slug": "keith-hufnagel-huf"}, {"id": 1421, "name": "drake jones", "slug": "drake-jones"}, {"id": 1517, "name": "ben liversedge", "slug": "ben-liversedge"}, {"id": 1193, "name": "shawn mandoli", "slug": "shawn-mandoli"}, {"id": 1788, "name": "gabe morford", "slug": "gabe-morford"}, {"id": 75, "name": "max schaaf", "slug": "max-schaaf"}, {"id": 1195, "name": "jim thiebaud", "slug": "jim-thiebaud"}, {"id": 6903, "name": "jaime reyes", "slug": "jaime-reyes"}], "tags": []}, {"id": 1184, "created_at": "2021-11-01T15:51:43.751120", "updated_at": "2021-11-01T15:51:43.751120", "slug": "sacrifice-in-through-the-out-door", "title": "Sacrifice - In Through The Out Door", "image_url": "https://assets.skatevideo.site/covers/sacrifice-in-through-the-out-door.jpg", "description": "", "year": 2004, "time": 0, "trailer": "", "videolink": "", "date": null, "is_active": true, "links": null, "category": {"id": 11, "name": "full-length"}, "filmmakers": [], "companies": [{"id": 331, "name": "sacrifice skateboards", "slug": "sacrifice-skateboards"}], "country": {"id": 0, "name": "Unknown"}, "soundtracks": [], "skaters": [{"id": 3100, "name": "brant austin", "slug": "brant-austin"}, {"id": 3101, "name": "rose bernfeld", "slug": "rose-bernfeld"}, {"id": 1424, "name": "ben butler", "slug": "ben-butler"}, {"id": 3102, "name": "chris farrell", "slug": "chris-farrell"}, {"id": 3103, "name": "jeff greenwood", "slug": "jeff-greenwood"}, {"id": 3104, "name": "mike hamerla", "slug": "mike-hamerla"}, {"id": 730, "name": "tony loco", "slug": "tony-loco"}, {"id": 3105, "name": "jonny manak", "slug": "jonny-manak"}, {"id": 3106, "name": "evandro menezes", "slug": "evandro-menezes"}, {"id": 3107, "name": "art miranda", "slug": "art-miranda"}, {"id": 3108, "name": "kyle mitchell", "slug": "kyle-mitchell"}, {"id": 3109, "name": "dave nelson", "slug": "dave-nelson"}, {"id": 3110, "name": "seferino nieto", "slug": "seferino-nieto"}, {"id": 3111, "name": "cressey rice", "slug": "cressey-rice"}, {"id": 3112, "name": "bart saric", "slug": "bart-saric"}, {"id": 2979, "name": "paul smith", "slug": "paul-smith"}], "tags": []}, {"id": 1163, "created_at": "2021-11-01T15:51:43.751120", "updated_at": "2021-11-01T15:51:43.751120", "slug": "payless-shoesource-trick-tips-with-andy-mac", "title": "Payless ShoeSource - Trick Tips With Andy Mac", "image_url": "https://assets.skatevideo.site/covers/payless-shoesource-trick-tips-with-andy-mac.jpg", "description": "", "year": 2002, "time": 10, "trailer": "", "videolink": "", "date": null, "is_active": true, "links": null, "category": {"id": 9, "name": "instructional"}, "filmmakers": [], "companies": [], "country": {"id": 0, "name": "Unknown"}, "soundtracks": [], "skaters": [{"id": 1055, "name": "andy macDonald", "slug": "andy-macDonald"}], "tags": []}, {"id": 1219, "created_at": "2021-11-01T15:51:43.751120", "updated_at": "2021-11-01T15:51:43.751120", "slug": "nsa-86-volume-1", "title": "NSA 86' Vol. 1", "image_url": "https://skatevideo.site/svs-192x192.png", "description": "", "year": 1986, "time": 60, "trailer": "", "videolink": "", "date": null, "is_active": true, "links": null, "category": {"id": 5, "name": "contest"}, "filmmakers": [], "companies": [{"id": 353, "name": "unreel productions", "slug": "unreel-productions"}], "country": {"id": 4, "name": "United States"}, "soundtracks": [], "skaters": [{"id": 883, "name": "john gibson", "slug": "john-gibson"}, {"id": 277, "name": "tony hawk", "slug": "tony-hawk"}, {"id": 1243, "name": "christian hosoi", "slug": "christian-hosoi"}, {"id": 2003, "name": "lester kasai", "slug": "lester-kasai"}, {"id": 2836, "name": "allen losi", "slug": "allen-losi"}, {"id": 1044, "name": "tony magnusson", "slug": "tony-magnusson"}, {"id": 1177, "name": "mike mcGill", "slug": "mike-mcGill"}, {"id": 613, "name": "lance mountain", "slug": "lance-mountain"}, {"id": 1164, "name": "jason phillips", "slug": "jason-phillips"}, {"id": 2012, "name": "mark anthony rogowski (\"gator\")", "slug": "mark-anthony-rogowski-gator"}], "tags": []}, {"id": 1130, "created_at": "2021-11-01T15:51:43.751120", "updated_at": "2022-01-03T20:27:10.486091", "slug": "foundation-rolling-thunder", "title": "Foundation - Rolling Thunder", "image_url": "https://assets.skatevideo.site/covers/foundation-rolling-thunder.jpg", "description": "", "year": 1995, "time": 27, "trailer": "", "videolink": "", "date": null, "is_active": true, "links": null, "category": {"id": 11, "name": "full-length"}, "filmmakers": [], "companies": [{"id": 26, "name": "Foundation Skateboards", "slug": "foundation-skateboards"}], "country": {"id": 0, "name": "Unknown"}, "soundtracks": [{"id": 35912, "videoid": 1130, "section": "Intro", "track": "Jennifer 12 And The Ski Patrol - ?", "sort": 1}, {"id": 35913, "videoid": 1130, "section": "Montage 1 (OG)", "track": "Beastie Boys - Groove Holmes", "sort": 2}, {"id": 35914, "videoid": 1130, "section": "Heath Kirchart", "track": "No Refund - ?", "sort": 3}, {"id": 35915, "videoid": 1130, "section": "Steve Olson", "track": "?", "sort": 4}, {"id": 35916, "videoid": 1130, "section": "Wil Taylor", "track": "Velocity Girl - My Forgotten Favorite", "sort": 5}, {"id": 35917, "videoid": 1130, "section": "Frank Hirata", "track": "Frank Hirata - ?", "sort": 6}, {"id": 35918, "videoid": 1130, "section": "Josh Beagle", "track": "The Jon Spencer Blues Explosion - Greyhound", "sort": 7}, {"id": 35919, "videoid": 1130, "section": "Paul Sharpe", "track": "Boilermaker - Ladyfinger", "sort": 8}, {"id": 35920, "videoid": 1130, "section": "Steve Berra", "track": "Sugar - Clownmaster", "sort": 9}, {"id": 35921, "videoid": 1130, "section": "Montage 2", "track": "?", "sort": 10}, {"id": 35922, "videoid": 1130, "section": "Credits", "track": "Fluf - ?", "sort": 11}], "skaters": [{"id": 249, "name": "josh beagle", "slug": "josh-beagle"}, {"id": 314, "name": "steve berra", "slug": "steve-berra"}, {"id": 1000, "name": "frank hirata", "slug": "frank-hirata"}, {"id": 48, "name": "heath kirchart", "slug": "heath-kirchart"}, {"id": 633, "name": "steve olson", "slug": "steve-olson"}, {"id": 623, "name": "paul sharpe", "slug": "paul-sharpe"}, {"id": 117, "name": "chad muska", "slug": "chad-muska"}, {"id": 37, "name": "donny barley", "slug": "donny-barley"}, {"id": 134, "name": "ed templeton", "slug": "ed-templeton"}, {"id": 145, "name": "jamie thomas (\"the chief\")", "slug": "jamie-thomas-the-chief"}, {"id": 1320, "name": "panama dan (daniel zimmerman)", "slug": "panama-dan-daniel-zimmerman"}, {"id": 558, "name": "satva leung", "slug": "satva-leung"}], "tags": []}, {"id": 4201, "created_at": "2022-08-05T20:10:32.860953", "updated_at": "2022-10-02T21:54:05.207645", "slug": "dc-x-bronze-clocker-2-what-if-god-said", "title": "DC x Bronze : CLOCKER 2 - WHAT IF GOD SAID", "image_url": "https://assets.skatevideo.site/covers/dc-x-bronze-clocker-2-what-if-god-said-51115.jpg", "description": "", "year": 2022, "time": 12, "trailer": null, "videolink": "https://www.youtube.com/watch?v=9TMePPRwwSM", "date": "2022-08-05T20:10:32.860953+00:00", "is_active": true, "links": [], "category": {"id": 2, "name": "promo"}, "filmmakers": [{"id": 138, "name": "Peter Sidlauskas", "slug": "peter-sidlauskas"}], "companies": [{"id": 754, "name": "Bronze 56K", "slug": "bronze-56k"}, {"id": 18, "name": "DC shoes", "slug": "DC-shoes"}], "country": {"id": 4, "name": "United States"}, "soundtracks": [{"id": 38414, "videoid": 4201, "section": "1. Intro", "track": "?", "sort": 1}, {"id": 38415, "videoid": 4201, "section": "2. Adilson Pedro, John Shanahan", "track": "BC9000 - Lone Ranger", "sort": 2}, {"id": 38416, "videoid": 4201, "section": "3. Shaun Paul 1", "track": "Doctor Destroyer - Swarm", "sort": 3}, {"id": 38417, "videoid": 4201, "section": "4. Shaun Paul 2 (Hot Tub)", "track": "Oneohtrix Point Never - Nobody Here (Malibu Cover) + Insides - Darling Effect", "sort": 4}, {"id": 38418, "videoid": 4201, "section": "5. Wes Kremer, Will Marshall", "track": "Oneohtrix Point Never - Ships Without Meaning (Jungle Remix)", "sort": 5}, {"id": 38419, "videoid": 4201, "section": "6. Will Marshall, Jahmir Brown, Lucien Clarke, Justin Hearn", "track": "Robert Russell Bennett  - Danger Down Deep", "sort": 6}, {"id": 38420, "videoid": 4201, "section": "7. Isaiah Stines", "track": "Nguzunguzu - Skycell", "sort": 7}, {"id": 38421, "videoid": 4201, "section": "8. Josh Wilson 1", "track": "Beasters - Humiliation Fetish", "sort": 8}, {"id": 38422, "videoid": 4201, "section": "9. Josh Wilson 2", "track": "Dr. Alex Paterson - Loving You Live", "sort": 9}, {"id": 38423, "videoid": 4201, "section": "10. Credits", "track": "?", "sort": 10}], "skaters": [{"id": 13401, "name": "johnny cumaoglu", "slug": "johnny-cumaoglu"}, {"id": 12490, "name": "adilson pedro", "slug": "adilson-pedro"}, {"id": 12492, "name": "shaun paul", "slug": "shaun-paul"}, {"id": 13083, "name": "isaiah stines", "slug": "isaiah-stines"}, {"id": 12878, "name": "justin hearn", "slug": "justin-hearn"}, {"id": 11856, "name": "jahmir brown", "slug": "jahmir-brown"}, {"id": 10538, "name": "john shanahan", "slug": "john-shanahan"}, {"id": 6725, "name": "josh wilson", "slug": "josh-wilson"}, {"id": 2216, "name": "lucien clarke", "slug": "lucien-clarke"}, {"id": 2687, "name": "wes kremer", "slug": "wes-kremer"}, {"id": 1680, "name": "will marshall", "slug": "will-marshall"}], "tags": []}, {"id": 1295, "created_at": "2021-11-01T15:51:43.751120", "updated_at": "2022-05-29T22:30:53.068256", "slug": "the-hardway", "title": "The Hardway", "image_url": "https://skatevideo.site/svs-192x192.png", "description": "", "year": 2004, "time": 56, "trailer": "", "videolink": "", "date": null, "is_active": true, "links": [], "category": {"id": 8, "name": "homemade"}, "filmmakers": [], "companies": [], "country": {"id": 3, "name": "Portugal"}, "soundtracks": [{"id": 12448, "videoid": 1295, "section": "Intro", "track": "Red Carpet - Alright", "sort": 1}, {"id": 12449, "videoid": 1295, "section": "Jo\u00e3o Rel\u00f3gio", "track": "?", "sort": 2}, {"id": 12450, "videoid": 1295, "section": "Patrick Esteban, \"Bacalhau\", Rafael Santos", "track": "The Cure - Lovesong", "sort": 3}, {"id": 12451, "videoid": 1295, "section": "Ivo Santos", "track": "Killa Carltoon - Prisonniers Du Silence", "sort": 4}, {"id": 12452, "videoid": 1295, "section": "Razo Skateshop", "track": "2Pac - 2 Of Amerikaz Most Wanted", "sort": 5}, {"id": 12453, "videoid": 1295, "section": "Cristov\u00e3o Ver\u00edssimo & Andr\u00e9 Nogueira", "track": "Hanoi Rocks - Dead By Xmas", "sort": 6}, {"id": 12454, "videoid": 1295, "section": "Andr\u00e9 Gil, Corinhas, \"Pablo\", \"Tobias\"", "track": "Fischerspooner - Emerge", "sort": 7}, {"id": 12455, "videoid": 1295, "section": "Bruno Caixa", "track": "Massive Attack - Teardrop", "sort": 8}, {"id": 12456, "videoid": 1295, "section": "\"Lisboeta\", Christian Ruiz, \"Figgy\"", "track": "Dry Cell - Still Waiting", "sort": 9}, {"id": 12457, "videoid": 1295, "section": "Friends", "track": "Punk C Manteiga - ?", "sort": 10}, {"id": 12458, "videoid": 1295, "section": "Kids", "track": "The Beach Boys - I Get Around", "sort": 11}, {"id": 12459, "videoid": 1295, "section": "M\u00e1rio Santos", "track": "The Offspring - The Kids Aren't Alright", "sort": 12}, {"id": 12460, "videoid": 1295, "section": "Tiago Rel\u00f3gio", "track": "Europe - The Final Countdown", "sort": 13}, {"id": 12461, "videoid": 1295, "section": "Nuno Rel\u00f3gio #1", "track": "Iron Maiden - No More Lies", "sort": 14}, {"id": 12462, "videoid": 1295, "section": "Nuno Rel\u00f3gio #2", "track": "Children of Bodom - Warheart", "sort": 15}], "skaters": [{"id": 3546, "name": "andr\u00e9 gil", "slug": "andr-gil"}, {"id": 3547, "name": "andr\u00e9 nogueira", "slug": "andr-nogueira"}, {"id": 3548, "name": "bruno caixa", "slug": "bruno-caixa"}, {"id": 3549, "name": "christian ruiz", "slug": "christian-ruiz"}, {"id": 3550, "name": "cristov\u00e3o ver\u00edssimo", "slug": "cristovo-verssimo"}, {"id": 3551, "name": "ivo santos", "slug": "ivo-santos"}, {"id": 3552, "name": "jo\u00e3o rel\u00f3gio", "slug": "joo-relgio"}, {"id": 3553, "name": "m\u00e1rio santos", "slug": "mrio-santos"}, {"id": 2231, "name": "nuno rel\u00f3gio", "slug": "nuno-relgio"}, {"id": 3554, "name": "patrick esteban", "slug": "patrick-esteban"}, {"id": 3555, "name": "rafael santos", "slug": "rafael-santos"}, {"id": 3556, "name": "tiago rel\u00f3gio", "slug": "tiago-relgio"}], "tags": []}, {"id": 1167, "created_at": "2021-11-01T15:51:43.751120", "updated_at": "2022-03-20T03:20:50.391402", "slug": "planet-earth-cats-cradle", "title": "Planet Earth - Cat's Cradle", "image_url": "https://assets.skatevideo.site/covers/planet-earth-cats-cradle-15710.jpeg", "description": "", "year": 1994, "time": 18, "trailer": "", "videolink": "", "date": null, "is_active": true, "links": null, "category": {"id": 2, "name": "promo"}, "filmmakers": [], "companies": [{"id": 84, "name": "planet earth clothing", "slug": "planet-earth-clothing"}], "country": {"id": 0, "name": "Unknown"}, "soundtracks": [{"id": 25413, "videoid": 1167, "section": "Intro", "track": "Deee Lite - Deee Lite Theme", "sort": 1}, {"id": 25414, "videoid": 1167, "section": "Matt Schnurr #1", "track": "Souls Of Mischief - That's When Ya Lost", "sort": 2}, {"id": 25415, "videoid": 1167, "section": "Dorian Tucker", "track": "The Damned - Love Song", "sort": 3}, {"id": 25416, "videoid": 1167, "section": "Kien Lieu", "track": "Cypress Hill - I Wanna Get High", "sort": 4}, {"id": 25417, "videoid": 1167, "section": "David Mills", "track": "David Bowie - Ashes To Ashes", "sort": 5}, {"id": 25418, "videoid": 1167, "section": "Ricky Higgins", "track": "The Pharcyde - Ya Mama", "sort": 6}, {"id": 25419, "videoid": 1167, "section": "Brian Howard", "track": "Digable Planets - Good To Be Here", "sort": 7}, {"id": 25420, "videoid": 1167, "section": "Mirko Mangum", "track": "The Beatles - Love Me Do", "sort": 8}, {"id": 25421, "videoid": 1167, "section": "Lib Layraman", "track": "Ren & Stimpy - Happy Happy Joy Joy", "sort": 9}, {"id": 25422, "videoid": 1167, "section": "Jason King", "track": "Pixies - Manta Rays", "sort": 10}, {"id": 25423, "videoid": 1167, "section": "Mark Wyndham", "track": "Stones - Get Off Of My Cloud", "sort": 11}, {"id": 25424, "videoid": 1167, "section": "Felix Arguelles", "track": "95 South - Whoot There It Is", "sort": 12}, {"id": 22741, "videoid": 1167, "section": "Jason Carney", "track": "Cypress Hill - Hits From The Bong", "sort": 13}, {"id": 25425, "videoid": 1167, "section": "Matt Schnurr #2", "track": "Souls Of Mischief - That's When Ya Lost", "sort": 14}, {"id": 25426, "videoid": 1167, "section": "Credits", "track": "Deee Lite - World Clique", "sort": 15}], "skaters": [{"id": 1121, "name": "felix arguelles", "slug": "felix-arguelles"}, {"id": 1073, "name": "jason carney", "slug": "jason-carney"}, {"id": 1645, "name": "ricky higgins", "slug": "ricky-higgins"}, {"id": 1018, "name": "brian howard", "slug": "brian-howard"}, {"id": 1118, "name": "jason king", "slug": "jason-king"}, {"id": 1123, "name": "lib layraman", "slug": "lib-layraman"}, {"id": 1037, "name": "kien lieu (\"donger\")", "slug": "kien-lieu-donger"}, {"id": 1124, "name": "mirko mangum", "slug": "mirko-mangum"}, {"id": 1135, "name": "chris miller", "slug": "chris-miller"}, {"id": 3045, "name": "david mills", "slug": "david-mills"}, {"id": 1022, "name": "matt schnur", "slug": "matt-schnur"}, {"id": 1054, "name": "dorian tucker", "slug": "dorian-tucker"}, {"id": 874, "name": "mark wyndham", "slug": "mark-wyndham"}], "tags": []}, {"id": 1133, "created_at": "2021-11-01T15:51:43.751120", "updated_at": "2022-03-24T00:26:57.620092", "slug": "collage", "title": "Collage", "image_url": "https://assets.skatevideo.site/covers/collage.jpg", "description": "", "year": 2001, "time": 60, "trailer": "", "videolink": "", "date": null, "is_active": true, "links": null, "category": {"id": 1, "name": "independent"}, "filmmakers": [], "companies": [{"id": 374, "name": "friends productions", "slug": "friends-productions"}], "country": {"id": 4, "name": "United States"}, "soundtracks": [], "skaters": [{"id": 1145, "name": "mike crum", "slug": "mike-crum"}, {"id": 140, "name": "fred gall", "slug": "fred-gall"}, {"id": 629, "name": "rune glifberg", "slug": "rune-glifberg"}, {"id": 277, "name": "tony hawk", "slug": "tony-hawk"}, {"id": 1161, "name": "harold hunter", "slug": "harold-hunter"}, {"id": 1793, "name": "huy lee", "slug": "huy-lee"}, {"id": 1037, "name": "kien lieu (\"donger\")", "slug": "kien-lieu-donger"}, {"id": 958, "name": "danny minnick", "slug": "danny-minnick"}, {"id": 117, "name": "chad muska", "slug": "chad-muska"}, {"id": 186, "name": "tom penny", "slug": "tom-penny"}, {"id": 104, "name": "andrew reynolds (\"the boss\")", "slug": "andrew-reynolds-the-boss"}, {"id": 5, "name": "geoff rowley", "slug": "geoff-rowley"}, {"id": 1361, "name": "henry sanchez", "slug": "henry-sanchez"}, {"id": 97, "name": "willy santos", "slug": "willy-santos"}, {"id": 1010, "name": "sean sheffey", "slug": "sean-sheffey"}, {"id": 482, "name": "peter smolik", "slug": "peter-smolik"}, {"id": 29, "name": "daewon song", "slug": "daewon-song"}, {"id": 107, "name": "anthony van engelen (\"ave\")", "slug": "anthony-van-engelen-ave"}, {"id": 129, "name": "danny way", "slug": "danny-way"}], "tags": []}, {"id": 1174, "created_at": "2021-11-01T15:51:43.751120", "updated_at": "2021-11-01T15:51:43.751120", "slug": "powell-scenic-drive", "title": "Powell - Scenic Drive", "image_url": "https://assets.skatevideo.site/covers/powell-scenic-drive.jpg", "description": "", "year": 1995, "time": 38, "trailer": "", "videolink": "", "date": null, "is_active": true, "links": null, "category": {"id": 11, "name": "full-length"}, "filmmakers": [], "companies": [{"id": 65, "name": "powell skateboards", "slug": "powell-skateboards"}], "country": {"id": 0, "name": "Unknown"}, "soundtracks": [{"id": 11566, "videoid": 1174, "section": "intro", "track": "Santo & Johnny - Sleepwalk", "sort": 1}, {"id": 11567, "videoid": 1174, "section": "Mike Vallely", "track": "Bruce Springsteen - Johnny 99", "sort": 2}, {"id": 11568, "videoid": 1174, "section": "Mike Santarossa", "track": "Steely Dan - Do It Again", "sort": 3}, {"id": 11569, "videoid": 1174, "section": "Danny Wainwright", "track": "John Coltrane - Trane's Blues", "sort": 4}, {"id": 11570, "videoid": 1174, "section": "Summer tour", "track": "Steppenwolf - Born To Be Wild", "sort": 5}, {"id": 11571, "videoid": 1174, "section": "AMtrak", "track": "Angelo Badalamenti - Dance Of The Dream Man", "sort": 6}, {"id": 11572, "videoid": 1174, "section": "Jayme Fortune", "track": "Propagandhi - Showdown", "sort": 7}, {"id": 11573, "videoid": 1174, "section": "Jon Comer", "track": "David Bowie - Ziggy Stardust", "sort": 8}, {"id": 11574, "videoid": 1174, "section": "Charlie Wilkins", "track": "The Doors - Moonlight Drive", "sort": 9}, {"id": 11575, "videoid": 1174, "section": "Steve Caballero", "track": "Dance Hall Crashers - Queen For A Day", "sort": 10}, {"id": 11576, "videoid": 1174, "section": "alternate route", "track": "Bad Religion - Stranger Than Fiction", "sort": 11}, {"id": 11577, "videoid": 1174, "section": "Jason Ellis", "track": "Metallica - Metal Militia", "sort": 12}, {"id": 11578, "videoid": 1174, "section": "Gershon Mosley", "track": "Des'ree - Crazy Maze", "sort": 13}, {"id": 11579, "videoid": 1174, "section": "credits", "track": "The Specials's - Ghost Town", "sort": 14}], "skaters": [{"id": 169, "name": "mike vallely", "slug": "mike-vallely"}, {"id": 1188, "name": "mike santarossa", "slug": "mike-santarossa"}, {"id": 1162, "name": "danny wainwright", "slug": "danny-wainwright"}, {"id": 372, "name": "jayme fortune", "slug": "jayme-fortune"}, {"id": 58, "name": "jon comer", "slug": "jon-comer"}, {"id": 596, "name": "charlie wilkins", "slug": "charlie-wilkins"}, {"id": 632, "name": "steve caballero", "slug": "steve-caballero"}, {"id": 1130, "name": "jason ellis", "slug": "jason-ellis"}, {"id": 449, "name": "gershon mosley", "slug": "gershon-mosley"}], "tags": []}, {"id": 1754, "created_at": "2021-11-01T15:51:43.751120", "updated_at": "2022-05-30T23:18:24.488527", "slug": "cosmic-vomit", "title": "Cosmic Vomit", "image_url": "https://assets.skatevideo.site/covers/cosmic-vomit-46643.jpg", "description": "", "year": 2009, "time": 48, "trailer": "http://www.youtube.com/watch?v=aJXbWt-33NQ", "videolink": "https://vimeo.com/11933767", "date": null, "is_active": true, "links": [], "category": {"id": 1, "name": "independent"}, "filmmakers": [{"id": 129, "name": "Grant Yansura", "slug": "grant-yansura"}], "companies": [{"id": 612, "name": "rip n' dip", "slug": "rip-n-dip"}], "country": {"id": 4, "name": "United States"}, "soundtracks": [{"id": 16439, "videoid": 1754, "section": "Intro", "track": "Annuals - Brother", "sort": 1}, {"id": 16440, "videoid": 1754, "section": "Bert Wootton", "track": "Broken Social Scene Presents Kevin Drew - Farewell To The Pressure Kids", "sort": 2}, {"id": 16441, "videoid": 1754, "section": "Johan Stuckey", "track": "The Black Angels - Bloodhounds On My Trail", "sort": 3}, {"id": 16442, "videoid": 1754, "section": "Justin Fuller & Rysean Goods", "track": "The Warlocks - Caveman Rock", "sort": 4}, {"id": 16443, "videoid": 1754, "section": "Friends", "track": "The Broken West - Down In The Valley", "sort": 5}, {"id": 16444, "videoid": 1754, "section": "RIP N' DIP Friends", "track": "Crocodiles - I Wanna Kill", "sort": 6}, {"id": 16445, "videoid": 1754, "section": "Grant Yansura", "track": "The Soft Pack - Extinction", "sort": 7}, {"id": 16446, "videoid": 1754, "section": "Derek McLean #1", "track": "Dan Auerbach - Whispered Words", "sort": 8}, {"id": 16447, "videoid": 1754, "section": "Derek McLean #2", "track": "The Concretes - Sunsets", "sort": 9}, {"id": 16448, "videoid": 1754, "section": "Andrew Considine #1", "track": "Black Sabbath - After Forever", "sort": 10}, {"id": 16449, "videoid": 1754, "section": "Andrew Considine #2", "track": "The Beatles - Oh! Darling", "sort": 11}, {"id": 16450, "videoid": 1754, "section": "Credits", "track": "The Warlocks - The Midnight Sun", "sort": 12}, {"id": 16451, "videoid": 1754, "section": "Outro #1", "track": "Billy Joel - Only The Good Die Young", "sort": 13}, {"id": 16452, "videoid": 1754, "section": "Outro #2", "track": "Berry White - You Sexy Thing", "sort": 14}, {"id": 16453, "videoid": 1754, "section": "Trailer", "track": "A Silver Mount Zion - 1000000 Died To Make This Sound", "sort": 15}], "skaters": [{"id": 4372, "name": "bert wootton", "slug": "bert-wootton"}, {"id": 1899, "name": "johan stuckey", "slug": "johan-stuckey"}, {"id": 4794, "name": "justin fuller", "slug": "justin-fuller"}, {"id": 4795, "name": "rysean goods", "slug": "rysean-goods"}, {"id": 4796, "name": "grant yansura", "slug": "grant-yansura"}, {"id": 4797, "name": "derek mcLean", "slug": "derek-mcLean"}, {"id": 4798, "name": "andrew considine", "slug": "andrew-considine"}], "tags": []}, {"id": 1129, "created_at": "2021-11-01T15:51:43.751120", "updated_at": "2022-01-05T01:15:44.091641", "slug": "foundation-duty-now-for-the-future", "title": "Foundation - Duty Now For The Future", "image_url": "https://assets.skatevideo.site/covers/duty-now-for-the-future.jpg", "description": "", "year": 1997, "time": 20, "trailer": "", "videolink": "", "date": null, "is_active": true, "links": null, "category": {"id": 11, "name": "full-length"}, "filmmakers": [], "companies": [{"id": 26, "name": "Foundation Skateboards", "slug": "foundation-skateboards"}], "country": {"id": 0, "name": "Unknown"}, "soundtracks": [{"id": 20648, "videoid": 1129, "section": "Corporate Message", "track": "Devo - Devo Corporate Anthem", "sort": 1}, {"id": 20649, "videoid": 1129, "section": "Cartoon", "track": "The Drags - Dragsploitation...Now!", "sort": 2}, {"id": 20650, "videoid": 1129, "section": "Intro", "track": "Butthole Surfers - Space", "sort": 3}, {"id": 20651, "videoid": 1129, "section": "Giant Skateboard", "track": "Man Or Astro-Man? - Reverb 10,000", "sort": 4}, {"id": 20652, "videoid": 1129, "section": "Brad Staba", "track": "The Delta 72 - The R&B Of Membership (Introduction)", "sort": 5}, {"id": 20653, "videoid": 1129, "section": "Daniel Haney Slam Intro", "track": "Satan's Pilgrims - Soul Pilgrim", "sort": 6}, {"id": 20654, "videoid": 1129, "section": "Daniel Haney", "track": "Inch - For Duty And Humanity", "sort": 7}, {"id": 36041, "videoid": 1129, "section": "Jon West Intro", "track": "?", "sort": 8}, {"id": 36042, "videoid": 1129, "section": "Jon West", "track": "The Velvet Underground - Sweet Jane", "sort": 9}, {"id": 36043, "videoid": 1129, "section": "Credits #1", "track": "Man Or Astro-Man? - ______(Reverse Sync Moog Version)", "sort": 10}, {"id": 36044, "videoid": 1129, "section": "Credits #2", "track": "Hammerhead - Gremlin Stomp", "sort": 11}, {"id": 36045, "videoid": 1129, "section": "Credits #3", "track": "Devo - Be Stiff", "sort": 12}, {"id": 36046, "videoid": 1129, "section": "Credits #4", "track": "The Let Downs - Hot Topic", "sort": 13}], "skaters": [{"id": 794, "name": "daniel haney", "slug": "daniel-haney"}, {"id": 593, "name": "brad staba", "slug": "brad-staba"}, {"id": 827, "name": "jon west", "slug": "jon-west"}, {"id": 798, "name": "jason rogers", "slug": "jason-rogers"}, {"id": 1122, "name": "jerry fowler", "slug": "jerry-fowler"}, {"id": 278, "name": "moses itkonen", "slug": "moses-itkonen"}, {"id": 1057, "name": "wil taylor", "slug": "wil-taylor"}, {"id": 37, "name": "donny barley", "slug": "donny-barley"}, {"id": 13446, "name": "mike geiger", "slug": "mike-geiger"}, {"id": 13447, "name": "les ramsan", "slug": "les-ramsan"}], "tags": []}, {"id": 1157, "created_at": "2021-11-01T15:51:43.751120", "updated_at": "2022-05-25T23:52:59.987646", "slug": "fruit-of-the-vine", "title": "Fruit Of The Vine", "image_url": "https://assets.skatevideo.site/covers/fruit-of-the-vine-14241.jpeg", "description": "", "year": 2000, "time": 53, "trailer": "", "videolink": "https://youtu.be/E1cg34lTrYU", "date": null, "is_active": true, "links": [], "category": {"id": 4, "name": "documentary"}, "filmmakers": [], "companies": [{"id": 321, "name": "nichols charnoski", "slug": "nichols-charnoski"}], "country": {"id": 4, "name": "United States"}, "soundtracks": [{"id": 31936, "videoid": 1157, "section": "Intro", "track": "Marimba - Chris Larsen - Shakuhaci Michael Velasco - 'Intro Tune", "sort": 1}, {"id": 31937, "videoid": 1157, "section": "Skate Into", "track": "10-96 - Too Much Confusion", "sort": 2}, {"id": 31938, "videoid": 1157, "section": "Salbaland", "track": "Bad Religion - Fuck Armegeddon This is Hell", "sort": 3}, {"id": 31939, "videoid": 1157, "section": "The Baldy Pipe", "track": "Steve Alba - Living Room Guitar Jam", "sort": 4}, {"id": 31940, "videoid": 1157, "section": "Salton Sea", "track": "Steel Wool - Coffee and Grapefruit", "sort": 5}, {"id": 31941, "videoid": 1157, "section": "David \"Shaggy\" Palmer", "track": "The Crusties - Your Own Words", "sort": 6}, {"id": 31942, "videoid": 1157, "section": "Gonzales Pool", "track": "Clay Wheels - Fine Brown Mist", "sort": 7}, {"id": 31943, "videoid": 1157, "section": "Arizona", "track": "Charalambides - Hail To The Brightness", "sort": 8}, {"id": 31944, "videoid": 1157, "section": "Fresno - Pool Search", "track": "Barnyard Playboys - Funeral Parlor Death Trip 2001", "sort": 9}, {"id": 31945, "videoid": 1157, "section": "The Bay Area", "track": "Loudmouths - I'm so nazi", "sort": 10}, {"id": 31946, "videoid": 1157, "section": "The Northeast", "track": "Travel Interlude - Rob Erickson", "sort": 11}, {"id": 31947, "videoid": 1157, "section": "Southern Oregon", "track": "George Draguns - ?", "sort": 12}, {"id": 31948, "videoid": 1157, "section": "Warm Springs", "track": "John Lyons - Banjo Picken", "sort": 13}, {"id": 31949, "videoid": 1157, "section": "Seattle", "track": "Hubble Constant - Instrumental", "sort": 14}, {"id": 31952, "videoid": 1157, "section": "Notheast", "track": "Bells Of - Bittersweet", "sort": 15}, {"id": 31951, "videoid": 1157, "section": "Fort Devens - C Pool", "track": "Venom P Stinger - Full Circle", "sort": 16}, {"id": 31950, "videoid": 1157, "section": "Baltimore", "track": "Carte Blanche - ?", "sort": 17}], "skaters": [{"id": 637, "name": "tony alva", "slug": "tony-alva"}, {"id": 2772, "name": "tony farmer", "slug": "tony-farmer"}, {"id": 3031, "name": "mark hubbard (\"monk\")", "slug": "mark-hubbard-monk"}, {"id": 613, "name": "lance mountain", "slug": "lance-mountain"}, {"id": 842, "name": "david palmer", "slug": "david-palmer"}, {"id": 2771, "name": "mark scott (\"red\")", "slug": "mark-scott-red"}, {"id": 11620, "name": "dave ruel", "slug": "dave-ruel"}, {"id": 11621, "name": "curtis hsiang", "slug": "curtis-hsiang"}, {"id": 11622, "name": "chris lundry", "slug": "chris-lundry"}, {"id": 11623, "name": "mike swin", "slug": "mike-swin"}, {"id": 11624, "name": "pat quirk", "slug": "pat-quirk"}, {"id": 11625, "name": "andy culberson", "slug": "andy-culberson"}, {"id": 11626, "name": "scott smilley", "slug": "scott-smilley"}, {"id": 11627, "name": "jimmy moore", "slug": "jimmy-moore"}, {"id": 789, "name": "steve bailey", "slug": "steve-bailey"}, {"id": 11628, "name": "tyco", "slug": "tyco"}, {"id": 2774, "name": "texas dan", "slug": "texas-dan"}, {"id": 11629, "name": "matt neeley", "slug": "matt-neeley"}, {"id": 11630, "name": "brian bean", "slug": "brian-bean"}, {"id": 11631, "name": "matt mollen", "slug": "matt-mollen"}, {"id": 3033, "name": "matt dyke", "slug": "matt-dyke"}, {"id": 11632, "name": "steve rocha", "slug": "steve-rocha"}, {"id": 122, "name": "chris senn", "slug": "chris-senn"}, {"id": 11633, "name": "jaime stapula", "slug": "jaime-stapula"}, {"id": 728, "name": "neil heddings", "slug": "neil-heddings"}, {"id": 11634, "name": "glen charnoski", "slug": "glen-charnoski"}, {"id": 11635, "name": "nick henderson", "slug": "nick-henderson"}, {"id": 11636, "name": "punk rock man", "slug": "punk-rock-man"}, {"id": 11637, "name": "ozzie", "slug": "ozzie"}, {"id": 11638, "name": "pete the ox", "slug": "pete-the-ox"}, {"id": 11639, "name": "james powers", "slug": "james-powers"}, {"id": 5263, "name": "choppy omega", "slug": "choppy-omega"}, {"id": 11640, "name": "josh hearst", "slug": "josh-hearst"}, {"id": 1312, "name": "karl hubble", "slug": "karl-hubble"}, {"id": 1154, "name": "josh falk", "slug": "josh-falk"}, {"id": 1240, "name": "steve alba", "slug": "steve-alba"}], "tags": []}, {"id": 1158, "created_at": "2021-11-01T15:51:43.751120", "updated_at": "2022-04-03T03:02:34.800074", "slug": "northwest", "title": "Northwest", "image_url": "https://assets.skatevideo.site/covers/northwest.jpg", "description": "", "year": 2003, "time": 40, "trailer": "https://vimeo.com/7166023", "videolink": "", "date": null, "is_active": true, "links": null, "category": {"id": 4, "name": "documentary"}, "filmmakers": [], "companies": [{"id": 321, "name": "nichols charnoski", "slug": "nichols-charnoski"}], "country": {"id": 4, "name": "United States"}, "soundtracks": [], "skaters": [{"id": 118, "name": "chet childress", "slug": "chet-childress"}, {"id": 1308, "name": "pete colpits", "slug": "pete-colpits"}, {"id": 3033, "name": "matt dyke", "slug": "matt-dyke"}, {"id": 417, "name": "peter hewitt", "slug": "peter-hewitt"}, {"id": 3031, "name": "mark hubbard (\"monk\")", "slug": "mark-hubbard-monk"}, {"id": 630, "name": "ryan johnson", "slug": "ryan-johnson"}, {"id": 3034, "name": "ben krahn", "slug": "ben-krahn"}, {"id": 3035, "name": "jimmy marcus", "slug": "jimmy-marcus"}, {"id": 842, "name": "david palmer", "slug": "david-palmer"}, {"id": 1315, "name": "joel price", "slug": "joel-price"}, {"id": 2771, "name": "mark scott (\"red\")", "slug": "mark-scott-red"}], "tags": []}]
