[{"id": 2678, "created_at": "2021-11-01T15:51:43.751120", "updated_at": "2021-11-01T15:51:43.751120", "slug": "cliche-bon-voyage", "title": "Clich\u00e9 - Bon Voyage", "image_url": "https://assets.skatevideo.site/covers/cliche-bon-voyage.jpg", "description": "", "year": 2013, "time": 50, "trailer": "http://www.youtube.com/watch?v=Nc2zAKx2zrs", "videolink": "", "date": "2013-05-04T21:19:32+00:00", "is_active": true, "links": null, "category": {"id": 11, "name": "full-length"}, "filmmakers": [{"id": 661, "name": "Boris Proust", "slug": "boris-proust"}], "companies": [{"id": 14, "name": "cliche skateboards", "slug": "cliche-skateboards"}], "country": {"id": 4, "name": "United States"}, "soundtracks": [{"id": 26749, "videoid": 2678, "section": "Intro", "track": "Busy P - Rainbow Man", "sort": 1}, {"id": 26750, "videoid": 2678, "section": "Daniel Espinoza", "track": "Hooray for Earth - Sails", "sort": 2}, {"id": 26751, "videoid": 2678, "section": "JB Gillet & Pete Eldridge", "track": "Amadou & Mariam - Sabali", "sort": 3}, {"id": 26752, "videoid": 2678, "section": "Max Geronzi, Paul Hart & Adrien Coillard", "track": "The Shoes - Time to Dance (SebastiAn Remix)", "sort": 4}, {"id": 26754, "videoid": 2678, "section": "Joey Brezinski", "track": "Future Islands - Vireo's Eye", "sort": 5}, {"id": 26755, "videoid": 2678, "section": "Andrew Brophy, Charles Collet, Javier Mendizabal & Lem Villemin", "track": "Jimmie Rodgers - Kisses Sweeter Than Wine", "sort": 6}, {"id": 26756, "videoid": 2678, "section": "Trucker Tour", "track": "Cassius - I Love You So", "sort": 7}, {"id": 26757, "videoid": 2678, "section": "Lucas Puig & Jeremie Daclin", "track": "Oxmo Puccino and DJ Cream - Tiroir Caisse", "sort": 8}, {"id": 26758, "videoid": 2678, "section": "Sammy Winter", "track": "Funeral Suits - All Those Friendly People", "sort": 9}, {"id": 26759, "videoid": 2678, "section": "Kevin Bradley\r\n", "track": "Tyler, The Creator - Domo 23\r\n", "sort": 10}, {"id": 26760, "videoid": 2678, "section": "Flo Mirtain", "track": "Lee Fields and the Expressions - Faithful Man", "sort": 11}, {"id": 26761, "videoid": 2678, "section": "Credits / Flow", "track": "Ben Harper - Better Way (War Mix)", "sort": 12}, {"id": 26762, "videoid": 2678, "section": "Credits / End", "track": "Breakbot - Baby I'm Yours", "sort": 13}], "skaters": [{"id": 4822, "name": "Daniel Espinoza", "slug": "Daniel-Espinoza"}, {"id": 147, "name": "jB gillet", "slug": "jB-gillet"}, {"id": 83, "name": "pete eldridge", "slug": "pete-eldridge"}, {"id": 491, "name": "max geronzi", "slug": "max-geronzi"}, {"id": 6932, "name": "paul hart", "slug": "paul-hart"}, {"id": 57, "name": "joey brezinski", "slug": "joey-brezinski"}, {"id": 488, "name": "andrew brophy", "slug": "andrew-brophy"}, {"id": 428, "name": "charles collet", "slug": "charles-collet"}, {"id": 426, "name": "javier mendizabal", "slug": "javier-mendizabal"}, {"id": 389, "name": "lem villemin", "slug": "lem-villemin"}, {"id": 162, "name": "lucas puig", "slug": "lucas-puig"}, {"id": 2096, "name": "sammy winter", "slug": "sammy-winter"}, {"id": 8838, "name": "kevin bradley", "slug": "kevin-bradley"}, {"id": 3776, "name": "flo mirtain", "slug": "flo-mirtain"}, {"id": 5808, "name": "adrien coillard", "slug": "adrien-coillard"}, {"id": 1905, "name": "jeremie daclin", "slug": "jeremie-daclin"}], "tags": []}, {"id": 3725, "created_at": "2021-11-20T03:08:48.137064", "updated_at": "2022-03-20T14:51:39.479699", "slug": "vans-europe-presents-going-nowhere", "title": "Vans Europe Presents: Going Nowhere", "image_url": "https://assets.skatevideo.site/covers/vans-europe-presents-going-nowhere.png", "description": null, "year": 2021, "time": 19, "trailer": null, "videolink": "https://www.youtube.com/watch?v=OHFQtvL32Jk", "date": "2021-04-13T22:03:09+00:00", "is_active": true, "links": null, "category": {"id": 2, "name": "promo"}, "filmmakers": [{"id": 1011, "name": "Max Pack", "slug": "max-pack"}], "companies": [{"id": 86, "name": "vans", "slug": "vans"}], "country": {"id": 4, "name": "United States"}, "soundtracks": [{"id": 35407, "videoid": 3725, "section": "Intro", "track": "Eddy Current Suppression Ring - Insufficient Funds", "sort": 1}, {"id": 35408, "videoid": 3725, "section": "Montage #1 (Ruben L\u00fccke, Daniel Spiegel & Niklas Schaible)", "track": "Jhonny Thunders - You", "sort": 2}, {"id": 35409, "videoid": 3725, "section": "", "track": "Untitled - Can'T Put Your Arms A Memory", "sort": 3}, {"id": 35410, "videoid": 3725, "section": "", "track": "Montage #2 (Daniel Spiegel, Paul Zenner, Justen Ernst & Manu Mayr & Joscha Aicher) Giuni Russo - Suddenly I'M Alone", "sort": 4}, {"id": 35411, "videoid": 3725, "section": "Jan Hoffmann", "track": "Witch - Black Tears", "sort": 5}], "skaters": [{"id": 12999, "name": "danny stephen", "slug": "danny-stephen"}, {"id": 13000, "name": "jan hoffmann", "slug": "jan-hoffmann"}, {"id": 13001, "name": "justen ernst", "slug": "justen-ernst"}, {"id": 13002, "name": "julian ruhe", "slug": "julian-ruhe"}, {"id": 13003, "name": "manu mayr", "slug": "manu-mayr"}, {"id": 13004, "name": "marcel weber", "slug": "marcel-weber"}, {"id": 13005, "name": "ruben l\u00fccke", "slug": "ruben-lucke"}, {"id": 13006, "name": "daniel lepori", "slug": "daniel-lepori"}, {"id": 13007, "name": "tim rebensdorf", "slug": "tim-rebensdorf"}, {"id": 13008, "name": "willow voges", "slug": "willow-voges"}, {"id": 13009, "name": "niklas schaible", "slug": "niklas-schaible"}, {"id": 7477, "name": "conny mirbach", "slug": "conny-mirbach"}, {"id": 3781, "name": "daniel spiegel", "slug": "daniel-spiegel"}, {"id": 2317, "name": "kalle wiehn", "slug": "kalle-wiehn"}, {"id": 9321, "name": "marco kada", "slug": "marco-kada"}, {"id": 7581, "name": "Paul Zenner", "slug": "Paul-Zenner"}, {"id": 10562, "name": "roland hirsch", "slug": "roland-hirsch"}, {"id": 14868, "name": "joscha aicher", "slug": "joscha-aicher"}], "tags": []}, {"id": 2680, "created_at": "2021-11-01T15:51:43.751120", "updated_at": "2021-11-01T15:51:43.751120", "slug": "cliche--gypsea-tour", "title": "Cliche - Gypsea Tour", "image_url": "https://assets.skatevideo.site/covers/cliche--gypsea-tour.jpg", "description": "", "year": 2010, "time": 23, "trailer": "", "videolink": "", "date": "2013-05-07T13:28:17+00:00", "is_active": true, "links": null, "category": {"id": 3, "name": "tour"}, "filmmakers": [{"id": 328, "name": "Fred Mortagne (\"French Fred\")", "slug": "fred-mortagne-french-fred"}, {"id": 662, "name": "Junior", "slug": "junior"}], "companies": [{"id": 14, "name": "cliche skateboards", "slug": "cliche-skateboards"}], "country": {"id": 0, "name": "Unknown"}, "soundtracks": [{"id": 26782, "videoid": 2680, "section": "#1", "track": "King Khan and The Shrines - Sweet Tooth", "sort": 1}, {"id": 26783, "videoid": 2680, "section": "#2", "track": "Dim Dim - Stubby Neck", "sort": 2}, {"id": 26784, "videoid": 2680, "section": "#3", "track": "The Budos Band - Budos Rising", "sort": 3}, {"id": 26785, "videoid": 2680, "section": "#4", "track": "Blue Horns - Boots On", "sort": 4}, {"id": 26786, "videoid": 2680, "section": "", "track": "", "sort": 5}], "skaters": [{"id": 162, "name": "lucas puig", "slug": "lucas-puig"}, {"id": 426, "name": "javier mendizabal", "slug": "javier-mendizabal"}, {"id": 3776, "name": "flo mirtain", "slug": "flo-mirtain"}, {"id": 2096, "name": "sammy winter", "slug": "sammy-winter"}, {"id": 488, "name": "andrew brophy", "slug": "andrew-brophy"}, {"id": 423, "name": "ricardo fonseca", "slug": "ricardo-fonseca"}, {"id": 428, "name": "charles collet", "slug": "charles-collet"}, {"id": 1905, "name": "jeremie daclin", "slug": "jeremie-daclin"}, {"id": 14, "name": "benny fairfax", "slug": "benny-fairfax"}], "tags": []}, {"id": 2682, "created_at": "2021-11-01T15:51:43.751120", "updated_at": "2021-11-01T15:51:43.751120", "slug": "green-apple-video-x", "title": "Green Apple - Video X", "image_url": "https://assets.skatevideo.site/covers/green-apple-video-x.jpg", "description": "", "year": 2013, "time": 0, "trailer": "", "videolink": "", "date": "2013-05-13T11:51:18+00:00", "is_active": true, "links": null, "category": {"id": 7, "name": "skateshop"}, "filmmakers": [], "companies": [{"id": 412, "name": "green apple", "slug": "green-apple"}], "country": {"id": 9, "name": "Canada"}, "soundtracks": [{"id": 26792, "videoid": 2682, "section": "Nick Serduletz #1", "track": "Jeff Lynne - Video", "sort": 1}, {"id": 26800, "videoid": 2682, "section": "Nick Serduletz #2", "track": "York Redoubt - I Said Slightly", "sort": 2}, {"id": 26801, "videoid": 2682, "section": "Devon Welter #1", "track": "Black Dice - Pinball Wizard", "sort": 3}, {"id": 26802, "videoid": 2682, "section": "Devon Welter #2", "track": "Black Dice - Outer Body Drifter", "sort": 4}, {"id": 26803, "videoid": 2682, "section": "Devon Welter #3", "track": "Jimmy Dell - Sittin' On The Roof", "sort": 5}, {"id": 26804, "videoid": 2682, "section": "Evan Burchuk", "track": "DJ Hvad - Angst", "sort": 6}, {"id": 26805, "videoid": 2682, "section": "Justin Basset #1", "track": "DJ Hvad - Syntezieser Mellemspil", "sort": 7}, {"id": 26806, "videoid": 2682, "section": "Justin Basset #2", "track": "Eric Copeland - Whorehouse Blues", "sort": 8}, {"id": 26807, "videoid": 2682, "section": "Justin Basset #3", "track": "Mayhem - Necrolust", "sort": 9}, {"id": 26808, "videoid": 2682, "section": "Aaron Rosenblatt", "track": "Peter Gabriel - Excuse Me", "sort": 10}, {"id": 26809, "videoid": 2682, "section": "Friends", "track": "Kim Y0un9 Ill - Northside (Junt Mix)", "sort": 11}, {"id": 26810, "videoid": 2682, "section": "Chris Rossong", "track": "Eric Copeland - Fun Dink Death", "sort": 12}, {"id": 26811, "videoid": 2682, "section": "Cole Middleton", "track": "Nochexxx - Crying Bamboo (Badself Master 2)", "sort": 13}, {"id": 26812, "videoid": 2682, "section": "Kevin Friesen", "track": "Skinny Boys - Jock Box", "sort": 14}, {"id": 26813, "videoid": 2682, "section": "Chris Guzzi", "track": "Ninetynine - Panel (99's Love Edit)", "sort": 15}, {"id": 26814, "videoid": 2682, "section": "Mike Vince", "track": "Nick Marion Taylor - Suicide Hotline (eMGee Groove)", "sort": 16}, {"id": 26815, "videoid": 2682, "section": "Jeremy Gelfant, Jason Crolly & Mike McDermott", "track": "Allen Ginsberg, Paul McCartney & Philip Glass - The Ballad Of Skeletons", "sort": 17}, {"id": 26816, "videoid": 2682, "section": "Russ Milligan #1", "track": "Eric Copeland - UFOs Over Vampire City", "sort": 18}, {"id": 26817, "videoid": 2682, "section": "Russ Milligan #2", "track": "Shirley Ellis w/ The Hutch Orchestra & Chorus - Nitty Gritty", "sort": 19}, {"id": 26818, "videoid": 2682, "section": "Russ Milligan #3", "track": "KMD - Nitty Gritty", "sort": 20}, {"id": 26819, "videoid": 2682, "section": "Paul Liliani #1", "track": "Tim Souster - Journey Of The Sorcerer", "sort": 21}, {"id": 26820, "videoid": 2682, "section": "Paul Liliani #2", "track": "Boys Noize - What You Want", "sort": 22}, {"id": 26821, "videoid": 2682, "section": "Credits #1", "track": "Goodiepal - Pa Rovermaner Mavee", "sort": 23}, {"id": 26822, "videoid": 2682, "section": "Credits #2", "track": "Goodiepal - I Kirby's Dreamland", "sort": 24}, {"id": 26823, "videoid": 2682, "section": "Credits #3", "track": "Goodiepal - Stompur Nafferen", "sort": 25}], "skaters": [], "tags": []}, {"id": 2817, "created_at": "2021-11-01T15:51:43.751120", "updated_at": "2021-11-01T15:51:43.751120", "slug": "sml-wheels-good-times-are-coming", "title": "Sml Wheels - Good Times Are Coming", "image_url": "https://skatevideo.site/svs-192x192.png", "description": "", "year": 2014, "time": 14, "trailer": "", "videolink": "", "date": "2014-02-21T21:05:11+00:00", "is_active": true, "links": null, "category": {"id": 2, "name": "promo"}, "filmmakers": [], "companies": [{"id": 821, "name": "sml. wheels", "slug": "sml-wheels"}], "country": {"id": 4, "name": "United States"}, "soundtracks": [{"id": 27831, "videoid": 2817, "section": "", "track": "Temples - Keep In The Dark\r\n", "sort": 1}, {"id": 27832, "videoid": 2817, "section": "", "track": "Nick Drake - Been Smoking Too Long\r\n", "sort": 2}, {"id": 27833, "videoid": 2817, "section": "", "track": "Frank Sinatra - You Make Me Feel So Young\r\n", "sort": 3}, {"id": 27834, "videoid": 2817, "section": "", "track": "Creppy Trees - Enjoy Yourself\r\n", "sort": 4}, {"id": 27835, "videoid": 2817, "section": "", "track": "Matt Costa - Good Times", "sort": 5}], "skaters": [{"id": 4091, "name": "ben fisher", "slug": "ben-fisher"}, {"id": 9011, "name": "aidan campbell", "slug": "aidan-campbell"}, {"id": 7363, "name": "sammy montano", "slug": "sammy-montano"}, {"id": 5699, "name": "aaron herrington", "slug": "aaron-herrington"}, {"id": 5791, "name": "chris jones", "slug": "chris-jones"}, {"id": 2818, "name": "anton myhrvold", "slug": "anton-myhrvold"}, {"id": 2199, "name": "morgan smith", "slug": "morgan-smith"}, {"id": 1284, "name": "austyn gillette", "slug": "austyn-gillette"}, {"id": 31, "name": "danny garcia", "slug": "danny-garcia"}, {"id": 9224, "name": "miles silvas", "slug": "miles-silvas"}, {"id": 51, "name": "james craig", "slug": "james-craig"}, {"id": 85, "name": "raymond molinar", "slug": "raymond-molinar"}, {"id": 9226, "name": "javan campello", "slug": "javan-campello"}, {"id": 5274, "name": "Mark Suciu", "slug": "Mark-Suciu"}, {"id": 4550, "name": "christoph wildgrube", "slug": "christoph-wildgrube"}], "tags": []}, {"id": 3647, "created_at": "2021-11-16T15:35:38.106110", "updated_at": "2021-11-16T15:35:38.106110", "slug": "huf-keith-hufnagel-forever", "title": "HUF - Keith Hufnagel Forever", "image_url": "https://assets.skatevideo.site/covers/huf-keith-hufnagel-forever.jpg", "description": null, "year": 2020, "time": 6, "trailer": null, "videolink": "https://www.youtube.com/watch?v=GG3FDC5BJ4k", "date": "2020-11-02T04:57:31+00:00", "is_active": true, "links": null, "category": {"id": 18, "name": "solo part"}, "filmmakers": [{"id": 251, "name": "RB Umali", "slug": "rb-umali"}], "companies": [{"id": 809, "name": "huf", "slug": "huf"}], "country": null, "soundtracks": [{"id": 34757, "videoid": 3647, "section": "", "track": "Hanni El Khatib - Two Brothers", "sort": 0}], "skaters": [{"id": 61, "name": "keith hufnagel (\"huf\")", "slug": "keith-hufnagel-huf"}], "tags": []}, {"id": 2720, "created_at": "2021-11-01T15:51:43.751120", "updated_at": "2021-11-01T15:51:43.751120", "slug": "bronze-solo-jazz", "title": "Bronze - Solo Jazz", "image_url": "https://assets.skatevideo.site/covers/bronze-solo-jazz.jpg", "description": "", "year": 2013, "time": 21, "trailer": "", "videolink": "", "date": "2013-08-28T10:45:49+00:00", "is_active": true, "links": null, "category": {"id": 1, "name": "independent"}, "filmmakers": [{"id": 138, "name": "Peter Sidlauskas", "slug": "peter-sidlauskas"}], "companies": [{"id": 754, "name": "Bronze 56K", "slug": "bronze-56k"}], "country": {"id": 4, "name": "United States"}, "soundtracks": [{"id": 27771, "videoid": 2720, "section": "Intro", "track": "Hype Williams - Ooovrrr", "sort": 1}, {"id": 27772, "videoid": 2720, "section": "Dick Rizzo #1", "track": "Contact Lens - North Face Reign", "sort": 2}, {"id": 27114, "videoid": 2720, "section": "Dick Rizzo #2", "track": "Antwon - Underwater Tank Feat. Lil Ugly Mane", "sort": 3}, {"id": 27773, "videoid": 2720, "section": "Dick Rizzo #3", "track": "18 Carat Affair - Fashion", "sort": 4}, {"id": 27774, "videoid": 2720, "section": "Josh Wilson #1", "track": "Inga Copeland - Notitle", "sort": 5}, {"id": 27794, "videoid": 2720, "section": "Josh Wilson #2", "track": "Internet Club - Synergize", "sort": 6}, {"id": 27113, "videoid": 2720, "section": "Shawn Powers #1", "track": "Team Jordan - I Need A Moment", "sort": 7}, {"id": 27795, "videoid": 2720, "section": "Shawn Powers #2", "track": "Del Tha Funkee Homosapien \u2013 Burnt", "sort": 8}, {"id": 27118, "videoid": 2720, "section": "Kevin Tierney #1", "track": "50 Cent, Noreaga, Consequence & Punchline - Foul Play (Freestyle 1999)", "sort": 9}, {"id": 27796, "videoid": 2720, "section": "Kevin Tierney #2", "track": "Chuck Person - Eccojam B5", "sort": 10}, {"id": 27797, "videoid": 2720, "section": "Rob Gonyon #1", "track": "Max B - Give Dem Hoes Up", "sort": 11}, {"id": 27798, "videoid": 2720, "section": "Rob Gonyon #2", "track": "Ohbliv - 94 Bubble Jacket With The Gore Tex", "sort": 12}, {"id": 27793, "videoid": 2720, "section": "Montage #1", "track": "18 Carat Affair - Destructive Attitudes In Paris", "sort": 13}, {"id": 27116, "videoid": 2720, "section": "Derick Ziemkiewicz", "track": "Cam'Ron Feat Jules - Double Up", "sort": 14}, {"id": 27792, "videoid": 2720, "section": "Joseph Delgado", "track": "Ohbliv - Sharing The Indo", "sort": 15}, {"id": 27115, "videoid": 2720, "section": "Montage #2", "track": "Hype Williams - Your Girl Smells Chung When She Wears Dior", "sort": 16}, {"id": 27791, "videoid": 2720, "section": "Aaron Herrington", "track": "18 Carat Affair - Gestures", "sort": 17}, {"id": 27790, "videoid": 2720, "section": "Jason Carrol #1", "track": "Contact Lens - Good Question", "sort": 18}, {"id": 27789, "videoid": 2720, "section": "Jason Carrol #2", "track": "New Dreams LTD - Camaro", "sort": 19}, {"id": 27788, "videoid": 2720, "section": "Billy Mcfeely #1", "track": "18 Carat Affair - Discovery", "sort": 20}, {"id": 27112, "videoid": 2720, "section": "Billy Mcfeely #2", "track": "Hype Williams - Treated Her Badly", "sort": 21}, {"id": 27117, "videoid": 2720, "section": "Billy Mcfeely #3", "track": "Dean Blunt - The Narcissist Feat Inga Copeland", "sort": 22}, {"id": 32578, "videoid": 2720, "section": "Credits", "track": "?", "sort": 23}], "skaters": [{"id": 8980, "name": "dick rizzo", "slug": "dick-rizzo"}, {"id": 6725, "name": "josh wilson", "slug": "josh-wilson"}, {"id": 3714, "name": "shawn powers", "slug": "shawn-powers"}, {"id": 3721, "name": "kevin tierney", "slug": "kevin-tierney"}, {"id": 3719, "name": "rob gonyon", "slug": "rob-gonyon"}, {"id": 3724, "name": "derick ziemkiewicz", "slug": "derick-ziemkiewicz"}, {"id": 3723, "name": "joseph delgado", "slug": "joseph-delgado"}, {"id": 5699, "name": "aaron herrington", "slug": "aaron-herrington"}, {"id": 8981, "name": "jason carrol", "slug": "jason-carrol"}, {"id": 3715, "name": "billy mcFeely", "slug": "billy-mcFeely"}], "tags": []}, {"id": 2740, "created_at": "2021-11-01T15:51:43.751120", "updated_at": "2021-11-01T15:51:43.751120", "slug": "sociedade-em-panico", "title": "Sociedade em P\u00e2nico", "image_url": "https://skatevideo.site/svs-192x192.png", "description": "", "year": 2013, "time": 40, "trailer": "", "videolink": "", "date": "2013-11-07T13:57:57+00:00", "is_active": true, "links": null, "category": {"id": 1, "name": "independent"}, "filmmakers": [], "companies": [], "country": {"id": 12, "name": "Brazil"}, "soundtracks": [], "skaters": [{"id": 9026, "name": "junior pereira", "slug": "junior-pereira"}, {"id": 9027, "name": "marcos maciel", "slug": "marcos-maciel"}, {"id": 9028, "name": "ricardo oliveira", "slug": "ricardo-oliveira"}, {"id": 9029, "name": "diego eugenio", "slug": "diego-eugenio"}, {"id": 9030, "name": "thomas henrique \"chavinho\"", "slug": "thomas-henrique-chavinho"}, {"id": 9031, "name": "willians damascena", "slug": "willians-damascena"}, {"id": 9032, "name": "herniogenes microfone", "slug": "herniogenes-microfone"}], "tags": []}, {"id": 2784, "created_at": "2021-11-01T15:51:43.751120", "updated_at": "2021-11-01T15:51:43.751120", "slug": "brothers", "title": "BROTHERS", "image_url": "https://skatevideo.site/svs-192x192.png", "description": "BROTHERS is an independent video out of Vancouver, Canada. Supported by Freeride Boardshop, KingShit Magazine, Ultimate Distribution, and ourCaste", "year": 2013, "time": 39, "trailer": "http://www.youtube.com/watch?v=ncYEgp1A0t0", "videolink": "", "date": "2014-01-04T14:51:19+00:00", "is_active": true, "links": null, "category": {"id": 1, "name": "independent"}, "filmmakers": [{"id": 130, "name": "Briggs Ogloff", "slug": "briggs-ogloff"}], "companies": [], "country": {"id": 9, "name": "Canada"}, "soundtracks": [], "skaters": [{"id": 5156, "name": "robert jasiorkowski", "slug": "robert-jasiorkowski"}, {"id": 3237, "name": "mark johnson", "slug": "mark-johnson"}, {"id": 9104, "name": "keith henry", "slug": "keith-henry"}, {"id": 8473, "name": "tyler warren", "slug": "tyler-warren"}, {"id": 9105, "name": "carson cartier", "slug": "carson-cartier"}, {"id": 4809, "name": "stefen ursulan", "slug": "stefen-ursulan"}, {"id": 9106, "name": "clayton parsons", "slug": "clayton-parsons"}, {"id": 7080, "name": "tony myshlyaev", "slug": "tony-myshlyaev"}, {"id": 4812, "name": "kurt oldach", "slug": "kurt-oldach"}, {"id": 4814, "name": "taylor christensen", "slug": "taylor-christensen"}, {"id": 9107, "name": "mickenzie keller", "slug": "mickenzie-keller"}, {"id": 4816, "name": "skylar kehr", "slug": "skylar-kehr"}, {"id": 9108, "name": "drew summersides", "slug": "drew-summersides"}], "tags": []}, {"id": 2715, "created_at": "2021-11-01T15:51:43.751120", "updated_at": "2021-11-01T15:51:43.751120", "slug": "new-balance-a-place-in-the-sun", "title": "New Balance - A Place In The Sun", "image_url": "https://skatevideo.site/svs-192x192.png", "description": "", "year": 2013, "time": 8, "trailer": "", "videolink": "", "date": "2013-08-16T15:52:01+00:00", "is_active": true, "links": null, "category": {"id": 2, "name": "promo"}, "filmmakers": [{"id": 346, "name": "Russell Houghten", "slug": "russell-houghten"}], "companies": [{"id": 802, "name": "new balance", "slug": "new-balance"}], "country": {"id": 4, "name": "United States"}, "soundtracks": [{"id": 27098, "videoid": 2715, "section": "Intro\r\n", "track": "Jonn Ollsin - ?\r\n", "sort": 1}, {"id": 27099, "videoid": 2715, "section": "Main\r\n", "track": "Sonic Youth - Purr", "sort": 2}], "skaters": [{"id": 173, "name": "pJ ladd", "slug": "pJ-ladd"}, {"id": 1, "name": "arto saari", "slug": "arto-saari"}, {"id": 1815, "name": "levi brown", "slug": "levi-brown"}, {"id": 4689, "name": "tom karangelov", "slug": "tom-karangelov"}, {"id": 5754, "name": "jordan taylor", "slug": "jordan-taylor"}, {"id": 2624, "name": "tyler surrey", "slug": "tyler-surrey"}], "tags": []}, {"id": 3727, "created_at": "2021-11-20T03:11:30.944577", "updated_at": "2021-11-20T03:11:30.944577", "slug": "volcom-que-saguaro", "title": "Volcom - Que Saguaro", "image_url": "https://assets.skatevideo.site/covers/volcom-que-saguaro.jpg", "description": null, "year": 2021, "time": 15, "trailer": null, "videolink": "https://youtu.be/MmU4jK2lnQA", "date": "2021-04-22T18:20:47+00:00", "is_active": true, "links": null, "category": {"id": 2, "name": "promo"}, "filmmakers": [{"id": 1069, "name": "Grant Amspacher", "slug": "grant-amspacher"}, {"id": 1070, "name": "Seth Huot", "slug": "seth-huot"}], "companies": [{"id": 49, "name": "volcom", "slug": "volcom"}], "country": {"id": 4, "name": "United States"}, "soundtracks": [{"id": 35416, "videoid": 3727, "section": "", "track": "Egadz - Handsmoke", "sort": 0}, {"id": 35417, "videoid": 3727, "section": "", "track": "The Line - Modem 2K (Instrumental)", "sort": 1}, {"id": 35418, "videoid": 3727, "section": "", "track": "Lee Paradise - Present To Ponder", "sort": 2}, {"id": 35419, "videoid": 3727, "section": "", "track": "Night Beats - New Day", "sort": 3}, {"id": 35420, "videoid": 3727, "section": "", "track": "Warish - Next To Pay", "sort": 4}, {"id": 35421, "videoid": 3727, "section": "", "track": "Big Hongry - Hongry Call The Cops", "sort": 5}, {"id": 35422, "videoid": 3727, "section": "", "track": "The Line - Don'T Drink My Whine", "sort": 6}], "skaters": [{"id": 13011, "name": "jamie lynn", "slug": "jamie-lynn"}, {"id": 13012, "name": "scott blum", "slug": "scott-blum"}, {"id": 7723, "name": "alec majerus", "slug": "alec-majerus"}, {"id": 1028, "name": "chris livingston", "slug": "chris-livingston"}, {"id": 11010, "name": "cj collins", "slug": "cj-collins"}, {"id": 26, "name": "collin provost", "slug": "collin-provost"}, {"id": 4014, "name": "mathias torres", "slug": "mathias-torres"}, {"id": 8390, "name": "milton martinez", "slug": "milton-martinez"}, {"id": 406, "name": "omar hassan", "slug": "omar-hassan"}, {"id": 417, "name": "peter hewitt", "slug": "peter-hewitt"}, {"id": 11616, "name": "simon bannerot", "slug": "simon-bannerot"}, {"id": 4963, "name": "tom remillard", "slug": "tom-remillard"}], "tags": []}, {"id": 1850, "created_at": "2021-11-01T15:51:43.751120", "updated_at": "2022-09-19T14:56:58.674528", "slug": "first-try", "title": "First Try", "image_url": "https://assets.skatevideo.site/covers/first-try.jpg", "description": "", "year": 2009, "time": 30, "trailer": "http://www.youtube.com/watch?v=Ok6tmkJ7gpg", "videolink": "", "date": null, "is_active": true, "links": null, "category": {"id": 8, "name": "homemade"}, "filmmakers": [], "companies": [], "country": {"id": 4, "name": "United States"}, "soundtracks": [{"id": 17423, "videoid": 1850, "section": "Intro", "track": "Headlights - School Boys", "sort": 1}, {"id": 17424, "videoid": 1850, "section": "Ryan Lodzinski", "track": "Ladytron - Tomorrow", "sort": 2}, {"id": 17425, "videoid": 1850, "section": "Johnnie Ingram #1", "track": "Carl Carlton - Everlasting Love", "sort": 3}, {"id": 17426, "videoid": 1850, "section": "Johnnie Ingram #2", "track": "The Kooks - Naive", "sort": 4}, {"id": 17427, "videoid": 1850, "section": "Friends", "track": "Islands - Rough Gem", "sort": 5}, {"id": 17428, "videoid": 1850, "section": "Blake Waldren", "track": "Modest Mouse - Dashboard", "sort": 6}, {"id": 17429, "videoid": 1850, "section": "Tyler Lodzinski (Intro)", "track": "Beach Boys - I Get Around", "sort": 7}, {"id": 17430, "videoid": 1850, "section": "Tyler Lodzinski", "track": "Albert Hammond Jr. - Call An Ambulance", "sort": 8}, {"id": 17431, "videoid": 1850, "section": "Credits", "track": "The Ramones - My Brain Is Hanging Upside Down (Bonzo Goes to Bitburg)", "sort": 9}], "skaters": [{"id": 5194, "name": "ryan lodzinski", "slug": "ryan-lodzinski"}, {"id": 5195, "name": "johnnie ingram", "slug": "johnnie-ingram"}, {"id": 5196, "name": "blake waldren", "slug": "blake-waldren"}, {"id": 5197, "name": "tyler lodzinski", "slug": "tyler-lodzinski"}], "tags": []}, {"id": 2811, "created_at": "2021-11-01T15:51:43.751120", "updated_at": "2021-11-01T15:51:43.751120", "slug": "salt-n-pepper", "title": "Salt 'N Pepper", "image_url": "https://skatevideo.site/svs-192x192.png", "description": "", "year": 2013, "time": 9, "trailer": "https://www.youtube.com/watch?v=LUCV7oyyPZM", "videolink": "", "date": "2014-02-16T17:26:07+00:00", "is_active": true, "links": null, "category": {"id": 17, "name": "web"}, "filmmakers": [{"id": 31, "name": "Elliott Vecchia", "slug": "elliott-vecchia"}], "companies": [], "country": {"id": 4, "name": "United States"}, "soundtracks": [{"id": 27799, "videoid": 2811, "section": "Intro #1", "track": "Wayans Brothers - Intro Theme\r\n", "sort": 1}, {"id": 27800, "videoid": 2811, "section": "Intro #2", "track": "A Tribe Called Quest - Electric Relaxation\r\n", "sort": 2}, {"id": 27801, "videoid": 2811, "section": "", "track": "Young Jeezy - Welcome Back\r\n", "sort": 3}, {"id": 27802, "videoid": 2811, "section": "", "track": "R. Kelly - I Believe I Can Fly\r\n", "sort": 4}, {"id": 27803, "videoid": 2811, "section": "", "track": "Big Pun - 100%\r\n", "sort": 5}, {"id": 27804, "videoid": 2811, "section": "", "track": "Urge Overkill - Girl You'll Be A Woman Soon\r\n", "sort": 6}, {"id": 27805, "videoid": 2811, "section": "", "track": "Big Twan - My Mic (Instrumental)", "sort": 7}, {"id": 27806, "videoid": 2811, "section": "", "track": "Salt-N-Pepa - Push It", "sort": 8}], "skaters": [{"id": 1679, "name": "dave bachinsky", "slug": "dave-bachinsky"}, {"id": 2001, "name": "manny santiago", "slug": "manny-santiago"}], "tags": []}, {"id": 1849, "created_at": "2021-11-01T15:51:43.751120", "updated_at": "2022-09-19T14:56:58.674014", "slug": "fun-promo", "title": "Fun Promo", "image_url": "https://assets.skatevideo.site/covers/fun-promo.jpg", "description": "", "year": 2009, "time": 22, "trailer": "", "videolink": "", "date": null, "is_active": true, "links": null, "category": null, "filmmakers": [], "companies": [], "country": {"id": 43, "name": "Colombia"}, "soundtracks": [{"id": 17412, "videoid": 1849, "section": "Intro", "track": "Are you feeling it - Teddy bears", "sort": 1}, {"id": 17413, "videoid": 1849, "section": "Jean Carlos Arias", "track": "Cashis - Pistol poppin", "sort": 2}, {"id": 17414, "videoid": 1849, "section": "Martin Rivera", "track": "Method man - Release yo delf", "sort": 3}, {"id": 17415, "videoid": 1849, "section": "Wilfer Arcila", "track": "Foreign beggars Noisia - Contact", "sort": 4}, {"id": 17416, "videoid": 1849, "section": "Jaime Bulla", "track": "Heart - Barracuda", "sort": 5}, {"id": 17417, "videoid": 1849, "section": "Damian Piedrahita", "track": "AC DC - Stiff upper lip", "sort": 6}, {"id": 17418, "videoid": 1849, "section": "Juan Davila", "track": "Covenant - Unforgiven", "sort": 7}, {"id": 17419, "videoid": 1849, "section": "Jhon Pardo", "track": "Rammstien - Zwitter", "sort": 8}, {"id": 17420, "videoid": 1849, "section": "Felipe Vasquez", "track": "Fat Joe Lil Wayne - Make it rain", "sort": 9}, {"id": 17421, "videoid": 1849, "section": "John Bejarano", "track": "Kanye West - Can't Tell Me Nothing", "sort": 10}, {"id": 17422, "videoid": 1849, "section": "Credits", "track": "Matisyahu - Got no water", "sort": 11}], "skaters": [{"id": 5185, "name": "jean carlos arias", "slug": "jean-carlos-arias"}, {"id": 5186, "name": "martin rivera", "slug": "martin-rivera"}, {"id": 5187, "name": "wilfer arcila", "slug": "wilfer-arcila"}, {"id": 5188, "name": "felipe vasquez", "slug": "felipe-vasquez"}, {"id": 5189, "name": "damian piedrahita", "slug": "damian-piedrahita"}, {"id": 5190, "name": "jaime bulla", "slug": "jaime-bulla"}, {"id": 5191, "name": "jhon pardo", "slug": "jhon-pardo"}, {"id": 5192, "name": "juan davila", "slug": "juan-davila"}, {"id": 5193, "name": "john bejarano", "slug": "john-bejarano"}], "tags": []}, {"id": 2746, "created_at": "2021-11-01T15:51:43.751120", "updated_at": "2021-11-01T15:51:43.751120", "slug": "salamat", "title": "Salamat", "image_url": "https://skatevideo.site/svs-192x192.png", "description": "A trip to Philippines with Alex Mizurov, Bastien Duverdier, Joseph Biais & Michael Mackrodt.\r\nFilmed and edited by Guillaume P\u00e9rimony\r\nAdditionnal filming by VJ Chua\r\nSupported by Planete Sport & Dakine.", "year": 2013, "time": 5, "trailer": "", "videolink": "", "date": "2013-11-18T18:51:47+00:00", "is_active": true, "links": null, "category": {"id": 3, "name": "tour"}, "filmmakers": [{"id": 114, "name": "Guillaume P\u00e9rimony", "slug": "guillaume-perimony"}], "companies": [], "country": {"id": 0, "name": "Unknown"}, "soundtracks": [{"id": 27344, "videoid": 2746, "section": "\r\n", "track": "Fleet Foxes - He Doesn't Know Why\r\n", "sort": 1}, {"id": 27345, "videoid": 2746, "section": "\r\n", "track": "Fleet Foxes - Peasant Song", "sort": 2}], "skaters": [{"id": 102, "name": "alex mizurov", "slug": "alex-mizurov"}, {"id": 4178, "name": "bastien duverdier", "slug": "bastien-duverdier"}, {"id": 2290, "name": "joseph biais", "slug": "joseph-biais"}, {"id": 289, "name": "michael mackrodt", "slug": "michael-mackrodt"}], "tags": []}, {"id": 2792, "created_at": "2021-11-01T15:51:43.751120", "updated_at": "2021-11-01T15:51:43.751120", "slug": "ashes-new-sheet", "title": "Ashes - New Sheet", "image_url": "https://skatevideo.site/svs-192x192.png", "description": "It's only 14 minutes long (including credits), but this is probably the longest video ever produced by a griptape company. How about that?", "year": 2013, "time": 14, "trailer": "", "videolink": "", "date": "2014-01-13T10:56:47+00:00", "is_active": true, "links": null, "category": {"id": 11, "name": "full-length"}, "filmmakers": [{"id": 293, "name": "Paul Labadie", "slug": "paul-labadie"}], "companies": [{"id": 815, "name": "ashes griptape", "slug": "ashes-griptape"}], "country": {"id": 0, "name": "Unknown"}, "soundtracks": [{"id": 27640, "videoid": 2792, "section": "intro", "track": "Dollar Brand - Whoza Mtwana\r\n", "sort": 1}, {"id": 27641, "videoid": 2792, "section": "#1", "track": "Michael And The Jesters - Screwdriver\r\n", "sort": 2}, {"id": 27642, "videoid": 2792, "section": "#2", "track": "Ennio Morricone - Farewell To Cheyenne\r\n", "sort": 3}, {"id": 27643, "videoid": 2792, "section": "Sebi Dorfer & Steve Forstner intro", "track": "Abdullah Ibrahim - Mamma\r\n", "sort": 4}, {"id": 27644, "videoid": 2792, "section": "Sebi Dorfer & Steve Forstner", "track": "Rory Gallagher - Eat My Words\r\n", "sort": 5}, {"id": 27645, "videoid": 2792, "section": "outro", "track": "Screamin' Jay Hawkins - Ashes", "sort": 6}], "skaters": [{"id": 518, "name": "phil zwijsen", "slug": "phil-zwijsen"}, {"id": 9125, "name": "jonathan thijs", "slug": "jonathan-thijs"}, {"id": 9126, "name": "anne olsacher", "slug": "anne-olsacher"}, {"id": 1245, "name": "oli buergin", "slug": "oli-buergin"}, {"id": 506, "name": "chris pfanner", "slug": "chris-pfanner"}, {"id": 5850, "name": "oscar candon", "slug": "oscar-candon"}, {"id": 4039, "name": "madars apse", "slug": "madars-apse"}, {"id": 289, "name": "michael mackrodt", "slug": "michael-mackrodt"}, {"id": 2823, "name": "sylvain tognelli", "slug": "sylvain-tognelli"}, {"id": 3386, "name": "dominik dietrich", "slug": "dominik-dietrich"}, {"id": 1937, "name": "muki rustig", "slug": "muki-rustig"}, {"id": 9127, "name": "sebi dorfer", "slug": "sebi-dorfer"}, {"id": 1962, "name": "steve forstner", "slug": "steve-forstner"}], "tags": []}, {"id": 2721, "created_at": "2021-11-01T15:51:43.751120", "updated_at": "2021-11-01T15:51:43.751120", "slug": "glue-factory-filler-3-months", "title": "Glue Factory - Filler 3 (Months)", "image_url": "https://assets.skatevideo.site/covers/glue-factory-filler-3-months.jpg", "description": "", "year": 2013, "time": 19, "trailer": "https://vimeo.com/69879137", "videolink": "", "date": "2013-09-01T03:18:57+00:00", "is_active": true, "links": null, "category": {"id": 11, "name": "full-length"}, "filmmakers": [{"id": 594, "name": "Ian Steig", "slug": "ian-steig"}], "companies": [{"id": 544, "name": "glue factory", "slug": "glue-factory"}], "country": {"id": 4, "name": "United States"}, "soundtracks": [{"id": 27119, "videoid": 2721, "section": "Dan Rusin\r\n", "track": "A-Ha - Riding The Crest\r\n", "sort": 1}, {"id": 27120, "videoid": 2721, "section": "Andrew Liebman\r\n", "track": "The Pharcyde - Passin' Me By\r\n", "sort": 2}, {"id": 27121, "videoid": 2721, "section": "Montage\r\n", "track": "Meatloaf - Paradise By The Dashboard Light\r\n", "sort": 3}, {"id": 27122, "videoid": 2721, "section": "Credits\r\n", "track": "Morrissey - The Never Played Symphonies", "sort": 4}], "skaters": [{"id": 5642, "name": "dan rusin", "slug": "dan-rusin"}, {"id": 5872, "name": "david nelson", "slug": "david-nelson"}, {"id": 8982, "name": "gabriel alsaker", "slug": "gabriel-alsaker"}, {"id": 1061, "name": "neal erickson", "slug": "neal-erickson"}, {"id": 1732, "name": "dan jackson", "slug": "dan-jackson"}, {"id": 1062, "name": "ryan hansen", "slug": "ryan-hansen"}, {"id": 991, "name": "chad benson", "slug": "chad-benson"}, {"id": 1734, "name": "jamiel nowparvar", "slug": "jamiel-nowparvar"}, {"id": 8142, "name": "andrew leibman", "slug": "andrew-leibman"}], "tags": []}, {"id": 2812, "created_at": "2021-11-01T15:51:43.751120", "updated_at": "2021-11-01T15:51:43.751120", "slug": "w8watchers", "title": "W8Watchers", "image_url": "https://skatevideo.site/svs-192x192.png", "description": "", "year": 2014, "time": 29, "trailer": "https://www.youtube.com/watch?v=RazbAtcbg2k", "videolink": "", "date": "2014-02-16T17:33:51+00:00", "is_active": true, "links": null, "category": {"id": 14, "name": "crew"}, "filmmakers": [], "companies": [], "country": {"id": 4, "name": "United States"}, "soundtracks": [{"id": 27807, "videoid": 2812, "section": "Intro", "track": "Goat and The Occasional Others - Luh Dat Shit\r\n", "sort": 1}, {"id": 27808, "videoid": 2812, "section": "Ryan Furrier", "track": "Young Jeezy - Jeezy The Snowman\r\n", "sort": 2}, {"id": 27809, "videoid": 2812, "section": "Dalton Jones #1", "track": "Nilson Schmilsson - Let The Good Times Roll\r\n", "sort": 3}, {"id": 27810, "videoid": 2812, "section": "Dalton Jones #2", "track": "Slim Thug - Funny\r\n", "sort": 4}, {"id": 27811, "videoid": 2812, "section": "Affiliate Section", "track": "Jonsoman - Funny Beat (Instrumental)\r\n", "sort": 5}, {"id": 27812, "videoid": 2812, "section": "Frat Section", "track": "Nipsey Hussle - Action Is Everything\r\n", "sort": 6}, {"id": 27813, "videoid": 2812, "section": "Homies Section", "track": "Wu-Tang Clan - Freestyle Live MTV\r\n", "sort": 7}, {"id": 27814, "videoid": 2812, "section": "Jack Lunt Lines", "track": "Jimi Hendrix - Little Wing\r\n", "sort": 8}, {"id": 27815, "videoid": 2812, "section": "Jack Lunt and Adrian Yimbo", "track": "Motorhead - Dance\r\n", "sort": 9}, {"id": 27816, "videoid": 2812, "section": "Credits", "track": "Green Day - Brain Stew\r\n", "sort": 10}, {"id": 27817, "videoid": 2812, "section": "Throwaway", "track": "The Shys - Ring Of Fire", "sort": 11}], "skaters": [{"id": 9221, "name": "ryan furrier", "slug": "ryan-furrier"}, {"id": 7558, "name": "dalton jones", "slug": "dalton-jones"}, {"id": 8144, "name": "jack lunt", "slug": "jack-lunt"}, {"id": 9222, "name": "adrian yimbo", "slug": "adrian-yimbo"}], "tags": []}, {"id": 2717, "created_at": "2021-11-01T15:51:43.751120", "updated_at": "2021-11-01T15:51:43.751120", "slug": "magenta-panic-in-gotham", "title": "Magenta - Panic In Gotham", "image_url": "https://assets.skatevideo.site/covers/magenta-panic-in-gotham.jpg", "description": "", "year": 2013, "time": 7, "trailer": "", "videolink": "", "date": "2013-08-20T02:00:24+00:00", "is_active": true, "links": null, "category": {"id": 2, "name": "promo"}, "filmmakers": [{"id": 261, "name": "Colin Read", "slug": "colin-read"}, {"id": 679, "name": "Vivien Feil", "slug": "vivien-feil"}], "companies": [{"id": 580, "name": "magenta skateboards", "slug": "magenta-skateboards"}], "country": {"id": 0, "name": "Unknown"}, "soundtracks": [{"id": 27101, "videoid": 2717, "section": "Montage", "track": "Leaders Of The New School - A Quarter To Cutthroat", "sort": 1}, {"id": 27102, "videoid": 2717, "section": "Leo Valls", "track": "Big L - Da Graveyard", "sort": 2}], "skaters": [{"id": 5401, "name": "leo valls", "slug": "leo-valls"}, {"id": 2281, "name": "vivien feil", "slug": "vivien-feil"}, {"id": 2458, "name": "soy panday", "slug": "soy-panday"}, {"id": 1417, "name": "jimmy lannon", "slug": "jimmy-lannon"}, {"id": 340, "name": "ben gore", "slug": "ben-gore"}, {"id": 2253, "name": "alex davis", "slug": "alex-davis"}, {"id": 8968, "name": "liu puli", "slug": "liu-puli"}, {"id": 1786, "name": "joel meinholz", "slug": "joel-meinholz"}, {"id": 8969, "name": "connor kammerer", "slug": "connor-kammerer"}, {"id": 6668, "name": "alex fogt", "slug": "alex-fogt"}, {"id": 8970, "name": "ryan barlow", "slug": "ryan-barlow"}, {"id": 3895, "name": "kenji nakahira", "slug": "kenji-nakahira"}, {"id": 624, "name": "quim cardona", "slug": "quim-cardona"}, {"id": 5854, "name": "masaki ui", "slug": "masaki-ui"}], "tags": []}, {"id": 2681, "created_at": "2021-11-01T15:51:43.751120", "updated_at": "2022-09-06T20:49:42.845349", "slug": "ambig-modern-art", "title": "Ambig - Modern Art", "image_url": "https://assets.skatevideo.site/covers/ambig-modern-art-38887.jpeg", "description": "", "year": 2013, "time": 17, "trailer": "vimeo.com/64601169", "videolink": "", "date": "2013-05-10T21:56:48+00:00", "is_active": true, "links": [], "category": {"id": 2, "name": "promo"}, "filmmakers": [], "companies": [{"id": 791, "name": "ambig Clothing", "slug": "ambig-Clothing"}], "country": {"id": 4, "name": "United States"}, "soundtracks": [{"id": 26787, "videoid": 2681, "section": "Intro\r\n", "track": "Stereolab - Golden Atoms", "sort": 1}, {"id": 26788, "videoid": 2681, "section": "Clive Dixon\r\n", "track": "Patti Smith - Pissing In A River", "sort": 2}, {"id": 26789, "videoid": 2681, "section": "Montage\r\n", "track": "Secret Machines - The Fire Is Waiting", "sort": 3}, {"id": 26790, "videoid": 2681, "section": "Matt Bennett\r\n", "track": "Bauhaus - Untitled", "sort": 4}, {"id": 26791, "videoid": 2681, "section": "Clint Walker\r\n", "track": "Holograms - Monolith", "sort": 5}], "skaters": [{"id": 8849, "name": "clive dixon", "slug": "clive-dixon"}, {"id": 381, "name": "jT aultz", "slug": "jT-aultz"}, {"id": 4958, "name": "sean conover", "slug": "sean-conover"}, {"id": 5431, "name": "clint walker", "slug": "clint-walker"}, {"id": 4472, "name": "Luis De Los Reyes", "slug": "Luis-De-Los-Reyes"}, {"id": 164, "name": "matt bennett", "slug": "matt-bennett"}], "tags": []}, {"id": 4295, "created_at": "2022-10-16T20:24:31.459713", "updated_at": "2022-10-17T22:20:51.419841", "slug": "burn-book", "title": "BURN BOOK", "image_url": "https://assets.skatevideo.site/covers/burn-book-37914.jpg", "description": "", "year": 2022, "time": 17, "trailer": null, "videolink": "https://youtu.be/pBYlcfKzOvk", "date": "2022-10-16T20:24:31.459713+00:00", "is_active": true, "links": [{"title": "Alternate Video Link", "url": "https://www.thrashermagazine.com/articles/trash/bottom-feeder-s-burn-book-video/"}], "category": {"id": 17, "name": "web"}, "filmmakers": [{"id": 1466, "name": "Chandler Burton", "slug": "chandler-burton"}, {"id": 1487, "name": "Mike Iemma", "slug": "mike-iemma"}], "companies": [], "country": {"id": 4, "name": "United States"}, "soundtracks": [{"id": 38889, "videoid": 4295, "section": "1", "track": "Ko Aka Koala - Pieces Of Me", "sort": 1}, {"id": 38890, "videoid": 4295, "section": "2", "track": "Ghost Carnage - Dirty Little Riddim Secret", "sort": 2}, {"id": 38891, "videoid": 4295, "section": "3", "track": "En Vogue - Don't Let Go (Love)", "sort": 3}, {"id": 38892, "videoid": 4295, "section": "4", "track": "Taking Back Sunday - Cute Without the \"E\" (Cut From the Team)", "sort": 4}, {"id": 38893, "videoid": 4295, "section": "5", "track": "My Chemical Romance - Welcome to the Black Parade (Steve Aoki 10th Anniversary Remix)", "sort": 5}, {"id": 38894, "videoid": 4295, "section": "6", "track": "?", "sort": 6}, {"id": 38895, "videoid": 4295, "section": "7", "track": "From First To Last - Emily", "sort": 7}, {"id": 38896, "videoid": 4295, "section": "8", "track": "Green Day - Wake Me Up When September Ends", "sort": 8}], "skaters": [{"id": 16334, "name": "benny gonzales", "slug": "benny-gonzales"}, {"id": 16335, "name": "liv black", "slug": "liv-black"}, {"id": 16327, "name": "jawn davis", "slug": "jawn-davis"}, {"id": 16338, "name": "zayah smith", "slug": "zayah-smith"}, {"id": 16328, "name": "dom irisoyen", "slug": "dom-irisoyen"}, {"id": 16329, "name": "maddie michno", "slug": "maddie-michno"}, {"id": 16331, "name": "brandon yuenger", "slug": "brandon-yuenger"}, {"id": 16330, "name": "mike iemma", "slug": "mike-iemma"}, {"id": 16336, "name": "nick ahmada", "slug": "nick-ahmada"}, {"id": 16340, "name": "joi tillman", "slug": "joi-tillman"}, {"id": 16344, "name": "fin argus", "slug": "fin-argus"}, {"id": 16332, "name": "dunya hary", "slug": "dunya-hary"}, {"id": 16333, "name": "joa field", "slug": "joa-field"}, {"id": 16339, "name": "sammy spiter", "slug": "sammy-spiter"}, {"id": 16342, "name": "jerrod la rue", "slug": "jerrod-la-rue"}, {"id": 16343, "name": "elia esparea", "slug": "elia-esparea"}, {"id": 16341, "name": "brandon nicholas", "slug": "brandon-nicholas"}, {"id": 12705, "name": "chandler burton (\"titus\")", "slug": "chandler-burton-titus"}, {"id": 15168, "name": "kien caples", "slug": "kien-caples"}, {"id": 15171, "name": "myles de courcy", "slug": "myles-de-courcy"}, {"id": 15303, "name": "hayden dean", "slug": "hayden-dean"}, {"id": 15387, "name": "neckface (\"nasty neckface\")", "slug": "neckface-nasty-neckface"}, {"id": 13343, "name": "lucas simora", "slug": "lucas-simora"}, {"id": 119, "name": "chris cole", "slug": "chris-cole"}, {"id": 3370, "name": "dane burman", "slug": "dane-burman"}, {"id": 8474, "name": "dustin henry", "slug": "dustin-henry"}, {"id": 11965, "name": "max wheeler", "slug": "max-wheeler"}, {"id": 5386, "name": "reuben barrack", "slug": "reuben-barrack"}], "tags": []}, {"id": 3726, "created_at": "2021-11-20T03:10:10.869543", "updated_at": "2022-07-15T19:44:27.867826", "slug": "volcom-born-to-blew", "title": "Volcom - Born to Blew", "image_url": "https://assets.skatevideo.site/covers/volcom-born-to-blew.jpg", "description": null, "year": 2020, "time": 13, "trailer": null, "videolink": "https://www.youtube.com/watch?v=jPGAb61tNTM", "date": "2020-05-28T23:19:12+00:00", "is_active": true, "links": [], "category": {"id": 3, "name": "tour"}, "filmmakers": [{"id": 116, "name": "Matt Bublitz", "slug": "matt-bublitz"}, {"id": 723, "name": "Lannie Rhoades", "slug": "lannie-rhoades"}, {"id": 1011, "name": "Max Pack", "slug": "max-pack"}, {"id": 1067, "name": "Christian Vankelst", "slug": "christian-vankelst"}], "companies": [{"id": 49, "name": "volcom", "slug": "volcom"}], "country": {"id": 16, "name": "Germany"}, "soundtracks": [{"id": 35412, "videoid": 3726, "section": "", "track": "Total Control - Black Spring", "sort": 1}, {"id": 35413, "videoid": 3726, "section": "", "track": "Joel Jerome - Everybody Wants Somebody", "sort": 2}, {"id": 35414, "videoid": 3726, "section": "", "track": "Tenor Saw - Pumpkin Belly", "sort": 3}, {"id": 35415, "videoid": 3726, "section": "", "track": "Goat - Bondye", "sort": 4}], "skaters": [{"id": 12716, "name": "doobie", "slug": "doobie"}, {"id": 506, "name": "chris pfanner", "slug": "chris-pfanner"}, {"id": 26, "name": "collin provost", "slug": "collin-provost"}, {"id": 219, "name": "grant taylor", "slug": "grant-taylor"}, {"id": 6128, "name": "harry lintell", "slug": "harry-lintell"}, {"id": 9415, "name": "jackson pilz", "slug": "jackson-pilz"}, {"id": 9334, "name": "jorge simoes", "slug": "jorge-simoes"}, {"id": 460, "name": "eniz fazliov", "slug": "eniz-fazliov"}], "tags": []}, {"id": 2691, "created_at": "2021-11-01T15:51:43.751120", "updated_at": "2022-05-14T20:05:30.518953", "slug": "what-time-when", "title": "What Time, When?", "image_url": "https://assets.skatevideo.site/covers/what-time-when-63073.jpg", "description": "", "year": 2013, "time": 69, "trailer": "https://youtu.be/XDF-QDDrlTc", "videolink": "https://www.youtube.com/user/vegasskating/search?query=What%20Time%2C%20When%3F", "date": "2013-05-29T08:14:49+00:00", "is_active": true, "links": [], "category": {"id": 1, "name": "independent"}, "filmmakers": [{"id": 667, "name": "Chris Gonzalez (\"Gonzo\")", "slug": "chris-gonzalez-gonzo"}], "companies": [], "country": {"id": 4, "name": "United States"}, "soundtracks": [{"id": 26861, "videoid": 2691, "section": "Montro", "track": "The Black Tambourines - Bad Days", "sort": 1}, {"id": 26862, "videoid": 2691, "section": "Frankie Decker #1", "track": "Wu-Tang Clan - Uzi (Pinky Ring)", "sort": 2}, {"id": 26863, "videoid": 2691, "section": "Frankie Decker #2", "track": "Ice Cube - Hello", "sort": 3}, {"id": 26864, "videoid": 2691, "section": "Jessy Jean Bart", "track": "Pixies - Nimrod Son", "sort": 4}, {"id": 26865, "videoid": 2691, "section": "Monmon", "track": "The White Wires - Pretty Girl", "sort": 5}, {"id": 26866, "videoid": 2691, "section": "Daniel Dent", "track": "Starfucker - Boy Toy", "sort": 6}, {"id": 26867, "videoid": 2691, "section": "Travis Kerr", "track": "Trick Daddy - I'm A Thug", "sort": 7}, {"id": 26868, "videoid": 2691, "section": "Jason Thurtle", "track": "The Black Tambourines - The White Album", "sort": 8}, {"id": 26869, "videoid": 2691, "section": "Cools #1", "track": "The White Stripes - We're Going To Be Friends", "sort": 9}, {"id": 26870, "videoid": 2691, "section": "Cools #2", "track": "Dr. Dog - Do The Trick", "sort": 10}, {"id": 26871, "videoid": 2691, "section": "Quincy \"Sleepy\" Dixon", "track": "George Benson - Give Me The Night", "sort": 11}, {"id": 26872, "videoid": 2691, "section": "Slackers", "track": "Girl Talk - Make Me Wanna", "sort": 12}, {"id": 26873, "videoid": 2691, "section": "Steve \"Black Ninja\" Osborne", "track": "DJ Nelson - Black Ninja", "sort": 13}, {"id": 26874, "videoid": 2691, "section": "Aryeh Kraus", "track": "Jessica Jalbert - Whatever, Whoever", "sort": 14}, {"id": 26875, "videoid": 2691, "section": "Addie Fridy", "track": "James - Laid", "sort": 15}, {"id": 26876, "videoid": 2691, "section": "Genesis Atkins", "track": "Alabama Shakes - You Ain't Alone", "sort": 16}, {"id": 26877, "videoid": 2691, "section": "Andrew \"Tinky\" Tomich #1", "track": "Sea Wolf - Wicked Blood", "sort": 17}, {"id": 26878, "videoid": 2691, "section": "Andrew \"Tinky\" Tomich #2", "track": "Danger Mouse & Sparklehorse - Just War", "sort": 18}, {"id": 26879, "videoid": 2691, "section": "Credits", "track": "A Tribe Called Quest - Buggin' Out", "sort": 19}], "skaters": [{"id": 8892, "name": "frankie decker", "slug": "frankie-decker"}, {"id": 8893, "name": "jessy jean bart (\"black sparrow\")", "slug": "jessy-jean-bart-black-sparrow"}, {"id": 8894, "name": "daniel dent", "slug": "daniel-dent"}, {"id": 8895, "name": "travis kerr", "slug": "travis-kerr"}, {"id": 8896, "name": "steve osborne", "slug": "steve-osborne"}, {"id": 5381, "name": "aryeh kraus", "slug": "aryeh-kraus"}, {"id": 8685, "name": "addie fridy", "slug": "addie-fridy"}, {"id": 8897, "name": "genesis atkins", "slug": "genesis-atkins"}, {"id": 8898, "name": "jacques robinson", "slug": "jacques-robinson"}, {"id": 7923, "name": "quincy dixon", "slug": "quincy-dixon"}, {"id": 6361, "name": "yohei miyazawa", "slug": "yohei-miyazawa"}, {"id": 7929, "name": "nick rodriguez", "slug": "nick-rodriguez"}, {"id": 8899, "name": "robert blazek", "slug": "robert-blazek"}, {"id": 8900, "name": "jason thurtle", "slug": "jason-thurtle"}, {"id": 8914, "name": "andrew tomich", "slug": "andrew-tomich"}], "tags": []}, {"id": 2758, "created_at": "2021-11-01T15:51:43.751120", "updated_at": "2021-11-01T15:51:43.751120", "slug": "tennskate-videophile", "title": "Tennskate - Videophile", "image_url": "https://assets.skatevideo.site/covers/tennskate-videophile.jpg", "description": "", "year": 2013, "time": 47, "trailer": "", "videolink": "", "date": "2013-12-15T12:01:52+00:00", "is_active": true, "links": null, "category": {"id": 1, "name": "independent"}, "filmmakers": [{"id": 692, "name": "Alex Rose", "slug": "alex-rose"}, {"id": 693, "name": "Josh Shupe", "slug": "josh-shupe"}], "companies": [{"id": 810, "name": "tennskate", "slug": "tennskate"}], "country": {"id": 4, "name": "United States"}, "soundtracks": [], "skaters": [{"id": 2493, "name": "ryan cooper", "slug": "ryan-cooper"}, {"id": 9072, "name": "jim arnold", "slug": "jim-arnold"}, {"id": 9073, "name": "chris long", "slug": "chris-long"}, {"id": 9074, "name": "chris burton", "slug": "chris-burton"}, {"id": 9075, "name": "hartman austin", "slug": "hartman-austin"}, {"id": 9076, "name": "nick guertin", "slug": "nick-guertin"}, {"id": 5623, "name": "james coleman", "slug": "james-coleman"}, {"id": 9077, "name": "chris scoggins", "slug": "chris-scoggins"}, {"id": 9078, "name": "nick turner", "slug": "nick-turner"}, {"id": 9079, "name": "jay mcdonald", "slug": "jay-mcdonald"}, {"id": 9080, "name": "fletcher renegar", "slug": "fletcher-renegar"}, {"id": 5629, "name": "cameron dell", "slug": "cameron-dell"}], "tags": []}, {"id": 2809, "created_at": "2021-11-01T15:51:43.751120", "updated_at": "2021-11-01T15:51:43.751120", "slug": "the-tropic-corridor", "title": "The Tropic Corridor", "image_url": "https://skatevideo.site/svs-192x192.png", "description": "", "year": 2014, "time": 14, "trailer": "", "videolink": "", "date": "2014-02-09T14:58:58+00:00", "is_active": true, "links": null, "category": {"id": 1, "name": "independent"}, "filmmakers": [{"id": 503, "name": "Michael Pearse", "slug": "michael-pearse"}], "companies": [], "country": {"id": 8, "name": "Australia"}, "soundtracks": [], "skaters": [{"id": 9211, "name": "andy nicholls", "slug": "andy-nicholls"}, {"id": 7742, "name": "louis riley", "slug": "louis-riley"}, {"id": 9212, "name": "dale mcdermott", "slug": "dale-mcdermott"}, {"id": 9213, "name": "chris craig", "slug": "chris-craig"}, {"id": 7743, "name": "marcus warren", "slug": "marcus-warren"}, {"id": 9214, "name": "cailean holland", "slug": "cailean-holland"}, {"id": 9215, "name": "andrew lovatt", "slug": "andrew-lovatt"}, {"id": 7334, "name": "anthony bull", "slug": "anthony-bull"}, {"id": 9216, "name": "andrew beauchamp", "slug": "andrew-beauchamp"}, {"id": 1246, "name": "tommy fynn", "slug": "tommy-fynn"}], "tags": []}]
